{"zoneId":854,"events":[{"id":"1","time":0,"name":"Start","text":"Start","activeTime":0,"lineNumber":9,"sortKey":0},{"id":"2","time":0,"name":"--sync--","text":"--sync--","activeTime":0,"lineNumber":10,"sortKey":1,"syncId":2},{"id":"3","time":10.5,"name":"--sync--","text":"--sync--","activeTime":0,"lineNumber":11,"sortKey":2,"syncId":3},{"id":"4","time":11.2,"name":"Doomvoid Cleaver","text":"Doomvoid Cleaver","activeTime":0,"lineNumber":12,"sortKey":3,"syncId":4},{"id":"5","time":25.4,"name":"Unholy Darkness","text":"Unholy Darkness","activeTime":0,"lineNumber":13,"sortKey":4,"syncId":5},{"id":"6","time":31.8,"name":"Slicer/Guillotine","text":"Slicer/Guillotine","activeTime":0,"lineNumber":14,"sortKey":5,"syncId":6},{"id":"7","time":43.8,"name":"Dark Fire III","text":"Dark Fire III","activeTime":0,"lineNumber":15,"sortKey":6,"syncId":7},{"id":"8","time":59.2,"name":"Spell-In-Waiting","text":"Spell-In-Waiting","activeTime":0,"lineNumber":16,"sortKey":7,"syncId":8},{"id":"9","time":69.3,"name":"Punishing Ray","text":"Punishing Ray","activeTime":0,"lineNumber":17,"sortKey":8,"syncId":9},{"id":"10","time":72.7,"name":"Spell-In-Waiting","text":"Spell-In-Waiting","activeTime":0,"lineNumber":18,"sortKey":9,"syncId":10},{"id":"11","time":86.1,"name":"Spell-In-Waiting","text":"Spell-In-Waiting","activeTime":0,"lineNumber":19,"sortKey":10,"syncId":11},{"id":"12","time":95.3,"name":"Dark Fire III","text":"Dark Fire III","activeTime":0,"lineNumber":20,"sortKey":11,"syncId":12},{"id":"13","time":105.3,"name":"Hell Wind","text":"Hell Wind","activeTime":0,"lineNumber":21,"sortKey":12,"syncId":13},{"id":"14","time":106.8,"name":"Shadoweye","text":"Shadoweye","activeTime":0,"lineNumber":22,"sortKey":13,"syncId":14},{"id":"15","time":106.8,"name":"Unholy Darkness","text":"Unholy Darkness","activeTime":0,"lineNumber":23,"sortKey":14,"syncId":15},{"id":"16","time":121.9,"name":"Shadowflame","text":"Shadowflame","activeTime":0,"lineNumber":24,"sortKey":15,"syncId":16},{"id":"17","time":134.1,"name":"Entropy","text":"Entropy","activeTime":0,"lineNumber":25,"sortKey":16,"syncId":17},{"id":"18","time":143.8,"name":"Empty Rage","text":"Empty Rage","activeTime":0,"lineNumber":26,"sortKey":17,"syncId":18},{"id":"19","time":148.7,"name":"Doomvoid Guillotine","text":"Doomvoid Guillotine","activeTime":0,"lineNumber":27,"sortKey":18,"syncId":19},{"id":"20","time":156.9,"name":"Doomvoid Slicer","text":"Doomvoid Slicer","activeTime":0,"lineNumber":28,"sortKey":19,"syncId":20},{"id":"21","time":164.9,"name":"Empty Hate","text":"Empty Hate","activeTime":0,"lineNumber":29,"sortKey":20,"syncId":21},{"id":"22","time":175.8,"name":"Doomvoid Cleaver","text":"Doomvoid Cleaver","activeTime":0,"lineNumber":30,"sortKey":21,"syncId":22},{"id":"23","time":191.2,"name":"Shadowflame","text":"Shadowflame","activeTime":0,"lineNumber":31,"sortKey":22,"syncId":23},{"id":"24","time":203.4,"name":"Entropy","text":"Entropy","activeTime":0,"lineNumber":32,"sortKey":23,"syncId":24},{"id":"25","time":208,"name":"Spell-In-Waiting","text":"Spell-In-Waiting","activeTime":0,"lineNumber":33,"sortKey":24,"syncId":25},{"id":"26","time":224.9,"name":"Flare","text":"Flare","activeTime":0,"lineNumber":34,"sortKey":25,"syncId":26},{"id":"27","time":229.3,"name":"Spell-In-Waiting","text":"Spell-In-Waiting","activeTime":0,"lineNumber":35,"sortKey":26,"syncId":27},{"id":"28","time":242.5,"name":"Hell Wind","text":"Hell Wind","activeTime":0,"lineNumber":36,"sortKey":27,"syncId":28},{"id":"29","time":248.5,"name":"Punishing Ray","text":"Punishing Ray","activeTime":0,"lineNumber":37,"sortKey":28,"syncId":29},{"id":"30","time":248.9,"name":"Shadoweye","text":"Shadoweye","activeTime":0,"lineNumber":38,"sortKey":29,"syncId":30},{"id":"31","time":260.7,"name":"Shadowflame","text":"Shadowflame","activeTime":0,"lineNumber":39,"sortKey":30,"syncId":31},{"id":"32","time":272.9,"name":"Entropy","text":"Entropy","activeTime":0,"lineNumber":40,"sortKey":31,"syncId":32},{"id":"33","time":282.9,"name":"Light/Dark Circles","text":"Light/Dark Circles","activeTime":0,"lineNumber":41,"sortKey":32},{"id":"34","time":286.4,"name":"Doomvoid Cleaver","text":"Doomvoid Cleaver","activeTime":0,"lineNumber":42,"sortKey":33,"syncId":34},{"id":"35","time":295.7,"name":"Unholy Darkness","text":"Unholy Darkness","activeTime":0,"lineNumber":43,"sortKey":34,"syncId":35},{"id":"36","time":304.1,"name":"Slicer/Guillotine","text":"Slicer/Guillotine","activeTime":0,"lineNumber":44,"sortKey":35,"syncId":36},{"id":"37","time":330.3,"name":"Shadowflame","text":"Shadowflame","activeTime":0,"lineNumber":45,"sortKey":36,"syncId":37},{"id":"38","time":342.5,"name":"Entropy","text":"Entropy","activeTime":0,"lineNumber":46,"sortKey":37,"syncId":38},{"id":"39","time":348.1,"name":"Spell-In-Waiting","text":"Spell-In-Waiting","activeTime":0,"lineNumber":47,"sortKey":38,"syncId":39},{"id":"40","time":358.2,"name":"Empty Hate/Rage","text":"Empty Hate/Rage","activeTime":0,"lineNumber":48,"sortKey":39,"syncId":40},{"id":"41","time":361.4,"name":"Spell-In-Waiting","text":"Spell-In-Waiting","activeTime":0,"lineNumber":49,"sortKey":40,"syncId":41},{"id":"42","time":374.7,"name":"Spell-In-Waiting","text":"Spell-In-Waiting","activeTime":0,"lineNumber":50,"sortKey":41,"syncId":42},{"id":"43","time":381.6,"name":"Flare","text":"Flare","activeTime":0,"lineNumber":51,"sortKey":42,"syncId":43},{"id":"44","time":386.9,"name":"Unholy Darkness","text":"Unholy Darkness","activeTime":0,"lineNumber":52,"sortKey":43,"syncId":44},{"id":"45","time":399.9,"name":"Shadowflame","text":"Shadowflame","activeTime":0,"lineNumber":53,"sortKey":44,"syncId":45},{"id":"46","time":408.5,"name":"Spell-In-Waiting","text":"Spell-In-Waiting","activeTime":0,"lineNumber":54,"sortKey":45,"syncId":46},{"id":"47","time":421.8,"name":"Spell-In-Waiting","text":"Spell-In-Waiting","activeTime":0,"lineNumber":55,"sortKey":46,"syncId":47},{"id":"48","time":430,"name":"Shadoweye","text":"Shadoweye","activeTime":0,"lineNumber":56,"sortKey":47,"syncId":48},{"id":"49","time":430,"name":"Flare","text":"Flare","activeTime":0,"lineNumber":57,"sortKey":48,"syncId":49},{"id":"50","time":437.4,"name":"Dark Fire III","text":"Dark Fire III","activeTime":0,"lineNumber":58,"sortKey":49,"syncId":50},{"id":"51","time":445.4,"name":"Light/Dark Circles","text":"Light/Dark Circles","activeTime":0,"lineNumber":59,"sortKey":50},{"id":"52","time":450.2,"name":"Punishing Ray","text":"Punishing Ray","activeTime":0,"lineNumber":60,"sortKey":51,"syncId":52},{"id":"53","time":455,"name":"Doomvoid Cleaver","text":"Doomvoid Cleaver","activeTime":0,"lineNumber":61,"sortKey":52,"syncId":53},{"id":"54","time":469.4,"name":"Shadowflame","text":"Shadowflame","activeTime":0,"lineNumber":62,"sortKey":53,"syncId":54},{"id":"55","time":499.2,"name":"Quietus","text":"Quietus","activeTime":0,"lineNumber":66,"sortKey":54,"syncId":55},{"id":"56","time":507.4,"name":"Cycle Of ?","text":"Cycle Of ?","activeTime":0,"lineNumber":67,"sortKey":55,"syncId":56},{"id":"57","time":510.5,"name":"Slicer/Guillotine?","text":"Slicer/Guillotine?","activeTime":0,"lineNumber":68,"sortKey":56,"syncId":57},{"id":"58","time":511.2,"name":"Cleaver/Slicer?","text":"Cleaver/Slicer?","activeTime":0,"lineNumber":69,"sortKey":57,"syncId":58},{"id":"59","time":513.6,"name":"Guillotine/Cleaver?","text":"Guillotine/Cleaver?","activeTime":0,"lineNumber":70,"sortKey":58,"syncId":59},{"id":"60","time":531.8,"name":"Cycle Of ?","text":"Cycle Of ?","activeTime":0,"lineNumber":72,"sortKey":59,"syncId":60},{"id":"61","time":534.9,"name":"Slicer/Guillotine?","text":"Slicer/Guillotine?","activeTime":0,"lineNumber":73,"sortKey":60,"syncId":61},{"id":"62","time":538,"name":"Cleaver/Slicer?","text":"Cleaver/Slicer?","activeTime":0,"lineNumber":74,"sortKey":61,"syncId":62},{"id":"63","time":538.7,"name":"Guillotine/Cleaver?","text":"Guillotine/Cleaver?","activeTime":0,"lineNumber":75,"sortKey":62,"syncId":63},{"id":"64","time":558.2,"name":"Quietus","text":"Quietus","activeTime":0,"lineNumber":77,"sortKey":63,"syncId":64},{"id":"65","time":568.2,"name":"Cycle Of ?","text":"Cycle Of ?","activeTime":0,"lineNumber":78,"sortKey":64,"syncId":65},{"id":"66","time":571.3,"name":"Slicer/Guillotine?","text":"Slicer/Guillotine?","activeTime":0,"lineNumber":79,"sortKey":65,"syncId":66},{"id":"67","time":574.4,"name":"Cleaver/Slicer?","text":"Cleaver/Slicer?","activeTime":0,"lineNumber":80,"sortKey":66},{"id":"68","time":575.1,"name":"Guillotine/Cleaver?","text":"Guillotine/Cleaver?","activeTime":0,"lineNumber":81,"sortKey":67},{"id":"69","time":593.2,"name":"Quietus","text":"Quietus","activeTime":0,"lineNumber":82,"sortKey":68,"syncId":69},{"id":"70","time":602.5,"name":"Quietus","text":"Quietus","activeTime":0,"lineNumber":83,"sortKey":69,"syncId":70},{"id":"71","time":611.8,"name":"Quietus","text":"Quietus","activeTime":0,"lineNumber":84,"sortKey":70,"syncId":71},{"id":"72","time":624.8,"name":"--sync--","text":"--sync--","activeTime":0,"lineNumber":85,"sortKey":71,"syncId":72},{"id":"73","time":629.8,"name":"Quietus Enrage","text":"Quietus Enrage","activeTime":0,"lineNumber":86,"sortKey":72}],"syncStart":[{"id":72,"regexType":"net","regex":"^20\\|[^|]*\\|[^|]*\\|Voidwalker\\|3E73\\|","start":-75.20000000000005,"end":629.8,"time":624.8,"lineNumber":85,"eventId":"72"},{"id":55,"regexType":"net","regex":"^2[12]\\|[^|]*\\|[^|]*\\|Voidwalker\\|3E71\\|","start":-0.8000000000000114,"end":519.2,"time":499.2,"lineNumber":66,"eventId":"55"},{"id":3,"regexType":"net","regex":"^2[12]\\|[^|]*\\|[^|]*\\|Voidwalker\\|3E63\\|","start":-0.5,"end":15.5,"time":10.5,"lineNumber":11,"eventId":"3"},{"id":2,"regexType":"net","regex":"^260\\|[^|]*\\|[^|]*\\|1\\|","start":0,"end":1,"time":0,"lineNumber":10,"eventId":"2"},{"id":4,"regexType":"net","regex":"^2[12]\\|[^|]*\\|[^|]*\\|Voidwalker\\|3E64\\|","start":8.7,"end":13.7,"time":11.2,"lineNumber":12,"eventId":"4"},{"id":5,"regexType":"net","regex":"^2[12]\\|[^|]*\\|[^|]*\\|Voidwalker\\|3E54\\|","start":22.9,"end":27.9,"time":25.4,"lineNumber":13,"eventId":"5"},{"id":6,"regexType":"net","regex":"^2[12]\\|[^|]*\\|[^|]*\\|Voidwalker\\|(?:3E4F|3E50)\\|","start":29.3,"end":34.3,"time":31.8,"lineNumber":14,"eventId":"6"},{"id":7,"regexType":"net","regex":"^2[12]\\|[^|]*\\|[^|]*\\|Voidwalker\\|3E57\\|","start":41.3,"end":46.3,"time":43.8,"lineNumber":15,"eventId":"7"},{"id":8,"regexType":"net","regex":"^2[12]\\|[^|]*\\|[^|]*\\|Voidwalker\\|3E52\\|","start":56.7,"end":61.7,"time":59.2,"lineNumber":16,"eventId":"8"},{"id":9,"regexType":"net","regex":"^2[12]\\|[^|]*\\|[^|]*\\|Voidwalker\\|3E5B\\|","start":66.8,"end":71.8,"time":69.3,"lineNumber":17,"eventId":"9"},{"id":10,"regexType":"net","regex":"^2[12]\\|[^|]*\\|[^|]*\\|Voidwalker\\|3E52\\|","start":70.2,"end":75.2,"time":72.7,"lineNumber":18,"eventId":"10"},{"id":11,"regexType":"net","regex":"^2[12]\\|[^|]*\\|[^|]*\\|Voidwalker\\|3E52\\|","start":83.6,"end":88.6,"time":86.1,"lineNumber":19,"eventId":"11"},{"id":12,"regexType":"net","regex":"^2[12]\\|[^|]*\\|[^|]*\\|Voidwalker\\|3E57\\|","start":92.8,"end":97.8,"time":95.3,"lineNumber":20,"eventId":"12"},{"id":13,"regexType":"net","regex":"^2[12]\\|[^|]*\\|[^|]*\\|Voidwalker\\|3E66\\|","start":102.8,"end":107.8,"time":105.3,"lineNumber":21,"eventId":"13"},{"id":14,"regexType":"net","regex":"^2[12]\\|[^|]*\\|[^|]*\\|Voidwalker\\|3E69\\|","start":104.3,"end":109.3,"time":106.8,"lineNumber":22,"eventId":"14"},{"id":15,"regexType":"net","regex":"^2[12]\\|[^|]*\\|[^|]*\\|Voidwalker\\|3E54\\|","start":104.3,"end":109.3,"time":106.8,"lineNumber":23,"eventId":"15"},{"id":16,"regexType":"net","regex":"^2[12]\\|[^|]*\\|[^|]*\\|Voidwalker\\|3E61\\|","start":119.4,"end":124.4,"time":121.9,"lineNumber":24,"eventId":"16"},{"id":17,"regexType":"net","regex":"^2[12]\\|[^|]*\\|[^|]*\\|Voidwalker\\|3E70\\|","start":131.6,"end":136.6,"time":134.1,"lineNumber":25,"eventId":"17"},{"id":18,"regexType":"net","regex":"^2[12]\\|[^|]*\\|[^|]*\\|Voidwalker\\|3E6C\\|","start":141.3,"end":146.3,"time":143.8,"lineNumber":26,"eventId":"18"},{"id":19,"regexType":"net","regex":"^2[12]\\|[^|]*\\|[^|]*\\|Voidwalker\\|3E4F\\|","start":146.2,"end":151.2,"time":148.7,"lineNumber":27,"eventId":"19"},{"id":20,"regexType":"net","regex":"^2[12]\\|[^|]*\\|[^|]*\\|Voidwalker\\|3E50\\|","start":154.4,"end":159.4,"time":156.9,"lineNumber":28,"eventId":"20"},{"id":21,"regexType":"net","regex":"^2[12]\\|[^|]*\\|[^|]*\\|Voidwalker\\|3E5A\\|","start":162.4,"end":167.4,"time":164.9,"lineNumber":29,"eventId":"21"},{"id":22,"regexType":"net","regex":"^2[12]\\|[^|]*\\|[^|]*\\|Voidwalker\\|3E64\\|","start":173.3,"end":178.3,"time":175.8,"lineNumber":30,"eventId":"22"},{"id":23,"regexType":"net","regex":"^2[12]\\|[^|]*\\|[^|]*\\|Voidwalker\\|3E61\\|","start":188.7,"end":193.7,"time":191.2,"lineNumber":31,"eventId":"23"},{"id":24,"regexType":"net","regex":"^2[12]\\|[^|]*\\|[^|]*\\|Voidwalker\\|3E70\\|","start":200.9,"end":205.9,"time":203.4,"lineNumber":32,"eventId":"24"},{"id":25,"regexType":"net","regex":"^2[12]\\|[^|]*\\|[^|]*\\|Voidwalker\\|3E52\\|","start":205.5,"end":210.5,"time":208,"lineNumber":33,"eventId":"25"},{"id":26,"regexType":"net","regex":"^2[12]\\|[^|]*\\|[^|]*\\|Voidwalker\\|4685\\|","start":222.4,"end":227.4,"time":224.9,"lineNumber":34,"eventId":"26"},{"id":27,"regexType":"net","regex":"^2[12]\\|[^|]*\\|[^|]*\\|Voidwalker\\|3E52\\|","start":226.8,"end":231.8,"time":229.3,"lineNumber":35,"eventId":"27"},{"id":28,"regexType":"net","regex":"^2[12]\\|[^|]*\\|[^|]*\\|Voidwalker\\|3E66\\|","start":240,"end":245,"time":242.5,"lineNumber":36,"eventId":"28"},{"id":29,"regexType":"net","regex":"^2[12]\\|[^|]*\\|[^|]*\\|Voidwalker\\|3E5B\\|","start":246,"end":251,"time":248.5,"lineNumber":37,"eventId":"29"},{"id":30,"regexType":"net","regex":"^2[12]\\|[^|]*\\|[^|]*\\|Voidwalker\\|3E69\\|","start":246.4,"end":251.4,"time":248.9,"lineNumber":38,"eventId":"30"},{"id":31,"regexType":"net","regex":"^2[12]\\|[^|]*\\|[^|]*\\|Voidwalker\\|3E61\\|","start":258.2,"end":263.2,"time":260.7,"lineNumber":39,"eventId":"31"},{"id":32,"regexType":"net","regex":"^2[12]\\|[^|]*\\|[^|]*\\|Voidwalker\\|3E70\\|","start":270.4,"end":275.4,"time":272.9,"lineNumber":40,"eventId":"32"},{"id":34,"regexType":"net","regex":"^2[12]\\|[^|]*\\|[^|]*\\|Voidwalker\\|3E64\\|","start":283.9,"end":288.9,"time":286.4,"lineNumber":42,"eventId":"34"},{"id":35,"regexType":"net","regex":"^2[12]\\|[^|]*\\|[^|]*\\|Voidwalker\\|3E54\\|","start":293.2,"end":298.2,"time":295.7,"lineNumber":43,"eventId":"35"},{"id":36,"regexType":"net","regex":"^2[12]\\|[^|]*\\|[^|]*\\|Voidwalker\\|(?:3E4F|3E50)\\|","start":301.6,"end":306.6,"time":304.1,"lineNumber":44,"eventId":"36"},{"id":37,"regexType":"net","regex":"^2[12]\\|[^|]*\\|[^|]*\\|Voidwalker\\|3E61\\|","start":327.8,"end":332.8,"time":330.3,"lineNumber":45,"eventId":"37"},{"id":38,"regexType":"net","regex":"^2[12]\\|[^|]*\\|[^|]*\\|Voidwalker\\|3E70\\|","start":340,"end":345,"time":342.5,"lineNumber":46,"eventId":"38"},{"id":39,"regexType":"net","regex":"^2[12]\\|[^|]*\\|[^|]*\\|Voidwalker\\|3E52\\|","start":345.6,"end":350.6,"time":348.1,"lineNumber":47,"eventId":"39"},{"id":40,"regexType":"net","regex":"^2[12]\\|[^|]*\\|[^|]*\\|Voidwalker\\|(?:3E5A|3E6C)\\|","start":355.7,"end":360.7,"time":358.2,"lineNumber":48,"eventId":"40"},{"id":41,"regexType":"net","regex":"^2[12]\\|[^|]*\\|[^|]*\\|Voidwalker\\|3E52\\|","start":358.9,"end":363.9,"time":361.4,"lineNumber":49,"eventId":"41"},{"id":42,"regexType":"net","regex":"^2[12]\\|[^|]*\\|[^|]*\\|Voidwalker\\|3E52\\|","start":372.2,"end":377.2,"time":374.7,"lineNumber":50,"eventId":"42"},{"id":43,"regexType":"net","regex":"^2[12]\\|[^|]*\\|[^|]*\\|Voidwalker\\|4685\\|","start":379.1,"end":384.1,"time":381.6,"lineNumber":51,"eventId":"43"},{"id":44,"regexType":"net","regex":"^2[12]\\|[^|]*\\|[^|]*\\|Voidwalker\\|3E54\\|","start":384.4,"end":389.4,"time":386.9,"lineNumber":52,"eventId":"44"},{"id":45,"regexType":"net","regex":"^2[12]\\|[^|]*\\|[^|]*\\|Voidwalker\\|3E61\\|","start":397.4,"end":402.4,"time":399.9,"lineNumber":53,"eventId":"45"},{"id":46,"regexType":"net","regex":"^2[12]\\|[^|]*\\|[^|]*\\|Voidwalker\\|3E52\\|","start":406,"end":411,"time":408.5,"lineNumber":54,"eventId":"46"},{"id":47,"regexType":"net","regex":"^2[12]\\|[^|]*\\|[^|]*\\|Voidwalker\\|3E52\\|","start":419.3,"end":424.3,"time":421.8,"lineNumber":55,"eventId":"47"},{"id":48,"regexType":"net","regex":"^2[12]\\|[^|]*\\|[^|]*\\|Voidwalker\\|3E69\\|","start":427.5,"end":432.5,"time":430,"lineNumber":56,"eventId":"48"},{"id":49,"regexType":"net","regex":"^2[12]\\|[^|]*\\|[^|]*\\|Voidwalker\\|4685\\|","start":427.5,"end":432.5,"time":430,"lineNumber":57,"eventId":"49"},{"id":50,"regexType":"net","regex":"^2[12]\\|[^|]*\\|[^|]*\\|Voidwalker\\|3E57\\|","start":434.9,"end":439.9,"time":437.4,"lineNumber":58,"eventId":"50"},{"id":52,"regexType":"net","regex":"^2[12]\\|[^|]*\\|[^|]*\\|Voidwalker\\|3E5B\\|","start":447.7,"end":452.7,"time":450.2,"lineNumber":60,"eventId":"52"},{"id":53,"regexType":"net","regex":"^2[12]\\|[^|]*\\|[^|]*\\|Voidwalker\\|3E64\\|","start":452.5,"end":457.5,"time":455,"lineNumber":61,"eventId":"53"},{"id":54,"regexType":"net","regex":"^2[12]\\|[^|]*\\|[^|]*\\|Voidwalker\\|3E61\\|","start":466.9,"end":471.9,"time":469.4,"lineNumber":62,"eventId":"54"},{"id":56,"regexType":"net","regex":"^2[12]\\|[^|]*\\|[^|]*\\|Voidwalker\\|(?:40B9|4659)\\|","start":504.9,"end":509.9,"time":507.4,"lineNumber":67,"eventId":"56"},{"id":57,"regexType":"net","regex":"^2[12]\\|[^|]*\\|[^|]*\\|Voidwalker\\|465A\\|","start":508,"end":513,"time":510.5,"lineNumber":68,"eventId":"57"},{"id":58,"regexType":"net","regex":"^2[12]\\|[^|]*\\|[^|]*\\|Voidwalker\\|3E64\\|","start":508.7,"end":513.7,"time":511.2,"lineNumber":69,"eventId":"58"},{"id":59,"regexType":"net","regex":"^2[12]\\|[^|]*\\|[^|]*\\|Voidwalker\\|465B\\|","start":511.1,"end":516.1,"time":513.6,"lineNumber":70,"eventId":"59"},{"id":60,"regexType":"net","regex":"^2[12]\\|[^|]*\\|[^|]*\\|Voidwalker\\|(?:40B9|4659)\\|","start":529.3,"end":534.3,"time":531.8,"lineNumber":72,"eventId":"60"},{"id":61,"regexType":"net","regex":"^2[12]\\|[^|]*\\|[^|]*\\|Voidwalker\\|40BA\\|","start":532.4,"end":537.4,"time":534.9,"lineNumber":73,"eventId":"61"},{"id":62,"regexType":"net","regex":"^2[12]\\|[^|]*\\|[^|]*\\|Voidwalker\\|40BB\\|","start":535.5,"end":540.5,"time":538,"lineNumber":74,"eventId":"62"},{"id":63,"regexType":"net","regex":"^2[12]\\|[^|]*\\|[^|]*\\|Voidwalker\\|3E64\\|","start":536.2,"end":541.2,"time":538.7,"lineNumber":75,"eventId":"63"},{"id":64,"regexType":"net","regex":"^2[12]\\|[^|]*\\|[^|]*\\|Voidwalker\\|3E71\\|","start":555.7,"end":560.7,"time":558.2,"lineNumber":77,"eventId":"64"},{"id":65,"regexType":"net","regex":"^2[12]\\|[^|]*\\|[^|]*\\|Voidwalker\\|(?:40B9|4659)\\|","start":565.7,"end":570.7,"time":568.2,"lineNumber":78,"eventId":"65"},{"id":66,"regexType":"net","regex":"^2[12]\\|[^|]*\\|[^|]*\\|Voidwalker\\|(?:40BA|465A)\\|","start":568.8,"end":573.8,"time":571.3,"lineNumber":79,"eventId":"66"},{"id":69,"regexType":"net","regex":"^2[12]\\|[^|]*\\|[^|]*\\|Voidwalker\\|3E71\\|","start":590.7,"end":595.7,"time":593.2,"lineNumber":82,"eventId":"69"},{"id":70,"regexType":"net","regex":"^2[12]\\|[^|]*\\|[^|]*\\|Voidwalker\\|3E71\\|","start":600,"end":605,"time":602.5,"lineNumber":83,"eventId":"70"},{"id":71,"regexType":"net","regex":"^2[12]\\|[^|]*\\|[^|]*\\|Voidwalker\\|3E71\\|","start":609.3,"end":614.3,"time":611.8,"lineNumber":84,"eventId":"71"}],"syncEnd":[{"id":2,"regexType":"net","regex":"^260\\|[^|]*\\|[^|]*\\|1\\|","start":0,"end":1,"time":0,"lineNumber":10,"eventId":"2"},{"id":4,"regexType":"net","regex":"^2[12]\\|[^|]*\\|[^|]*\\|Voidwalker\\|3E64\\|","start":8.7,"end":13.7,"time":11.2,"lineNumber":12,"eventId":"4"},{"id":3,"regexType":"net","regex":"^2[12]\\|[^|]*\\|[^|]*\\|Voidwalker\\|3E63\\|","start":-0.5,"end":15.5,"time":10.5,"lineNumber":11,"eventId":"3"},{"id":5,"regexType":"net","regex":"^2[12]\\|[^|]*\\|[^|]*\\|Voidwalker\\|3E54\\|","start":22.9,"end":27.9,"time":25.4,"lineNumber":13,"eventId":"5"},{"id":6,"regexType":"net","regex":"^2[12]\\|[^|]*\\|[^|]*\\|Voidwalker\\|(?:3E4F|3E50)\\|","start":29.3,"end":34.3,"time":31.8,"lineNumber":14,"eventId":"6"},{"id":7,"regexType":"net","regex":"^2[12]\\|[^|]*\\|[^|]*\\|Voidwalker\\|3E57\\|","start":41.3,"end":46.3,"time":43.8,"lineNumber":15,"eventId":"7"},{"id":8,"regexType":"net","regex":"^2[12]\\|[^|]*\\|[^|]*\\|Voidwalker\\|3E52\\|","start":56.7,"end":61.7,"time":59.2,"lineNumber":16,"eventId":"8"},{"id":9,"regexType":"net","regex":"^2[12]\\|[^|]*\\|[^|]*\\|Voidwalker\\|3E5B\\|","start":66.8,"end":71.8,"time":69.3,"lineNumber":17,"eventId":"9"},{"id":10,"regexType":"net","regex":"^2[12]\\|[^|]*\\|[^|]*\\|Voidwalker\\|3E52\\|","start":70.2,"end":75.2,"time":72.7,"lineNumber":18,"eventId":"10"},{"id":11,"regexType":"net","regex":"^2[12]\\|[^|]*\\|[^|]*\\|Voidwalker\\|3E52\\|","start":83.6,"end":88.6,"time":86.1,"lineNumber":19,"eventId":"11"},{"id":12,"regexType":"net","regex":"^2[12]\\|[^|]*\\|[^|]*\\|Voidwalker\\|3E57\\|","start":92.8,"end":97.8,"time":95.3,"lineNumber":20,"eventId":"12"},{"id":13,"regexType":"net","regex":"^2[12]\\|[^|]*\\|[^|]*\\|Voidwalker\\|3E66\\|","start":102.8,"end":107.8,"time":105.3,"lineNumber":21,"eventId":"13"},{"id":14,"regexType":"net","regex":"^2[12]\\|[^|]*\\|[^|]*\\|Voidwalker\\|3E69\\|","start":104.3,"end":109.3,"time":106.8,"lineNumber":22,"eventId":"14"},{"id":15,"regexType":"net","regex":"^2[12]\\|[^|]*\\|[^|]*\\|Voidwalker\\|3E54\\|","start":104.3,"end":109.3,"time":106.8,"lineNumber":23,"eventId":"15"},{"id":16,"regexType":"net","regex":"^2[12]\\|[^|]*\\|[^|]*\\|Voidwalker\\|3E61\\|","start":119.4,"end":124.4,"time":121.9,"lineNumber":24,"eventId":"16"},{"id":17,"regexType":"net","regex":"^2[12]\\|[^|]*\\|[^|]*\\|Voidwalker\\|3E70\\|","start":131.6,"end":136.6,"time":134.1,"lineNumber":25,"eventId":"17"},{"id":18,"regexType":"net","regex":"^2[12]\\|[^|]*\\|[^|]*\\|Voidwalker\\|3E6C\\|","start":141.3,"end":146.3,"time":143.8,"lineNumber":26,"eventId":"18"},{"id":19,"regexType":"net","regex":"^2[12]\\|[^|]*\\|[^|]*\\|Voidwalker\\|3E4F\\|","start":146.2,"end":151.2,"time":148.7,"lineNumber":27,"eventId":"19"},{"id":20,"regexType":"net","regex":"^2[12]\\|[^|]*\\|[^|]*\\|Voidwalker\\|3E50\\|","start":154.4,"end":159.4,"time":156.9,"lineNumber":28,"eventId":"20"},{"id":21,"regexType":"net","regex":"^2[12]\\|[^|]*\\|[^|]*\\|Voidwalker\\|3E5A\\|","start":162.4,"end":167.4,"time":164.9,"lineNumber":29,"eventId":"21"},{"id":22,"regexType":"net","regex":"^2[12]\\|[^|]*\\|[^|]*\\|Voidwalker\\|3E64\\|","start":173.3,"end":178.3,"time":175.8,"lineNumber":30,"eventId":"22"},{"id":23,"regexType":"net","regex":"^2[12]\\|[^|]*\\|[^|]*\\|Voidwalker\\|3E61\\|","start":188.7,"end":193.7,"time":191.2,"lineNumber":31,"eventId":"23"},{"id":24,"regexType":"net","regex":"^2[12]\\|[^|]*\\|[^|]*\\|Voidwalker\\|3E70\\|","start":200.9,"end":205.9,"time":203.4,"lineNumber":32,"eventId":"24"},{"id":25,"regexType":"net","regex":"^2[12]\\|[^|]*\\|[^|]*\\|Voidwalker\\|3E52\\|","start":205.5,"end":210.5,"time":208,"lineNumber":33,"eventId":"25"},{"id":26,"regexType":"net","regex":"^2[12]\\|[^|]*\\|[^|]*\\|Voidwalker\\|4685\\|","start":222.4,"end":227.4,"time":224.9,"lineNumber":34,"eventId":"26"},{"id":27,"regexType":"net","regex":"^2[12]\\|[^|]*\\|[^|]*\\|Voidwalker\\|3E52\\|","start":226.8,"end":231.8,"time":229.3,"lineNumber":35,"eventId":"27"},{"id":28,"regexType":"net","regex":"^2[12]\\|[^|]*\\|[^|]*\\|Voidwalker\\|3E66\\|","start":240,"end":245,"time":242.5,"lineNumber":36,"eventId":"28"},{"id":29,"regexType":"net","regex":"^2[12]\\|[^|]*\\|[^|]*\\|Voidwalker\\|3E5B\\|","start":246,"end":251,"time":248.5,"lineNumber":37,"eventId":"29"},{"id":30,"regexType":"net","regex":"^2[12]\\|[^|]*\\|[^|]*\\|Voidwalker\\|3E69\\|","start":246.4,"end":251.4,"time":248.9,"lineNumber":38,"eventId":"30"},{"id":31,"regexType":"net","regex":"^2[12]\\|[^|]*\\|[^|]*\\|Voidwalker\\|3E61\\|","start":258.2,"end":263.2,"time":260.7,"lineNumber":39,"eventId":"31"},{"id":32,"regexType":"net","regex":"^2[12]\\|[^|]*\\|[^|]*\\|Voidwalker\\|3E70\\|","start":270.4,"end":275.4,"time":272.9,"lineNumber":40,"eventId":"32"},{"id":34,"regexType":"net","regex":"^2[12]\\|[^|]*\\|[^|]*\\|Voidwalker\\|3E64\\|","start":283.9,"end":288.9,"time":286.4,"lineNumber":42,"eventId":"34"},{"id":35,"regexType":"net","regex":"^2[12]\\|[^|]*\\|[^|]*\\|Voidwalker\\|3E54\\|","start":293.2,"end":298.2,"time":295.7,"lineNumber":43,"eventId":"35"},{"id":36,"regexType":"net","regex":"^2[12]\\|[^|]*\\|[^|]*\\|Voidwalker\\|(?:3E4F|3E50)\\|","start":301.6,"end":306.6,"time":304.1,"lineNumber":44,"eventId":"36"},{"id":37,"regexType":"net","regex":"^2[12]\\|[^|]*\\|[^|]*\\|Voidwalker\\|3E61\\|","start":327.8,"end":332.8,"time":330.3,"lineNumber":45,"eventId":"37"},{"id":38,"regexType":"net","regex":"^2[12]\\|[^|]*\\|[^|]*\\|Voidwalker\\|3E70\\|","start":340,"end":345,"time":342.5,"lineNumber":46,"eventId":"38"},{"id":39,"regexType":"net","regex":"^2[12]\\|[^|]*\\|[^|]*\\|Voidwalker\\|3E52\\|","start":345.6,"end":350.6,"time":348.1,"lineNumber":47,"eventId":"39"},{"id":40,"regexType":"net","regex":"^2[12]\\|[^|]*\\|[^|]*\\|Voidwalker\\|(?:3E5A|3E6C)\\|","start":355.7,"end":360.7,"time":358.2,"lineNumber":48,"eventId":"40"},{"id":41,"regexType":"net","regex":"^2[12]\\|[^|]*\\|[^|]*\\|Voidwalker\\|3E52\\|","start":358.9,"end":363.9,"time":361.4,"lineNumber":49,"eventId":"41"},{"id":42,"regexType":"net","regex":"^2[12]\\|[^|]*\\|[^|]*\\|Voidwalker\\|3E52\\|","start":372.2,"end":377.2,"time":374.7,"lineNumber":50,"eventId":"42"},{"id":43,"regexType":"net","regex":"^2[12]\\|[^|]*\\|[^|]*\\|Voidwalker\\|4685\\|","start":379.1,"end":384.1,"time":381.6,"lineNumber":51,"eventId":"43"},{"id":44,"regexType":"net","regex":"^2[12]\\|[^|]*\\|[^|]*\\|Voidwalker\\|3E54\\|","start":384.4,"end":389.4,"time":386.9,"lineNumber":52,"eventId":"44"},{"id":45,"regexType":"net","regex":"^2[12]\\|[^|]*\\|[^|]*\\|Voidwalker\\|3E61\\|","start":397.4,"end":402.4,"time":399.9,"lineNumber":53,"eventId":"45"},{"id":46,"regexType":"net","regex":"^2[12]\\|[^|]*\\|[^|]*\\|Voidwalker\\|3E52\\|","start":406,"end":411,"time":408.5,"lineNumber":54,"eventId":"46"},{"id":47,"regexType":"net","regex":"^2[12]\\|[^|]*\\|[^|]*\\|Voidwalker\\|3E52\\|","start":419.3,"end":424.3,"time":421.8,"lineNumber":55,"eventId":"47"},{"id":48,"regexType":"net","regex":"^2[12]\\|[^|]*\\|[^|]*\\|Voidwalker\\|3E69\\|","start":427.5,"end":432.5,"time":430,"lineNumber":56,"eventId":"48"},{"id":49,"regexType":"net","regex":"^2[12]\\|[^|]*\\|[^|]*\\|Voidwalker\\|4685\\|","start":427.5,"end":432.5,"time":430,"lineNumber":57,"eventId":"49"},{"id":50,"regexType":"net","regex":"^2[12]\\|[^|]*\\|[^|]*\\|Voidwalker\\|3E57\\|","start":434.9,"end":439.9,"time":437.4,"lineNumber":58,"eventId":"50"},{"id":52,"regexType":"net","regex":"^2[12]\\|[^|]*\\|[^|]*\\|Voidwalker\\|3E5B\\|","start":447.7,"end":452.7,"time":450.2,"lineNumber":60,"eventId":"52"},{"id":53,"regexType":"net","regex":"^2[12]\\|[^|]*\\|[^|]*\\|Voidwalker\\|3E64\\|","start":452.5,"end":457.5,"time":455,"lineNumber":61,"eventId":"53"},{"id":54,"regexType":"net","regex":"^2[12]\\|[^|]*\\|[^|]*\\|Voidwalker\\|3E61\\|","start":466.9,"end":471.9,"time":469.4,"lineNumber":62,"eventId":"54"},{"id":56,"regexType":"net","regex":"^2[12]\\|[^|]*\\|[^|]*\\|Voidwalker\\|(?:40B9|4659)\\|","start":504.9,"end":509.9,"time":507.4,"lineNumber":67,"eventId":"56"},{"id":57,"regexType":"net","regex":"^2[12]\\|[^|]*\\|[^|]*\\|Voidwalker\\|465A\\|","start":508,"end":513,"time":510.5,"lineNumber":68,"eventId":"57"},{"id":58,"regexType":"net","regex":"^2[12]\\|[^|]*\\|[^|]*\\|Voidwalker\\|3E64\\|","start":508.7,"end":513.7,"time":511.2,"lineNumber":69,"eventId":"58"},{"id":59,"regexType":"net","regex":"^2[12]\\|[^|]*\\|[^|]*\\|Voidwalker\\|465B\\|","start":511.1,"end":516.1,"time":513.6,"lineNumber":70,"eventId":"59"},{"id":55,"regexType":"net","regex":"^2[12]\\|[^|]*\\|[^|]*\\|Voidwalker\\|3E71\\|","start":-0.8000000000000114,"end":519.2,"time":499.2,"lineNumber":66,"eventId":"55"},{"id":60,"regexType":"net","regex":"^2[12]\\|[^|]*\\|[^|]*\\|Voidwalker\\|(?:40B9|4659)\\|","start":529.3,"end":534.3,"time":531.8,"lineNumber":72,"eventId":"60"},{"id":61,"regexType":"net","regex":"^2[12]\\|[^|]*\\|[^|]*\\|Voidwalker\\|40BA\\|","start":532.4,"end":537.4,"time":534.9,"lineNumber":73,"eventId":"61"},{"id":62,"regexType":"net","regex":"^2[12]\\|[^|]*\\|[^|]*\\|Voidwalker\\|40BB\\|","start":535.5,"end":540.5,"time":538,"lineNumber":74,"eventId":"62"},{"id":63,"regexType":"net","regex":"^2[12]\\|[^|]*\\|[^|]*\\|Voidwalker\\|3E64\\|","start":536.2,"end":541.2,"time":538.7,"lineNumber":75,"eventId":"63"},{"id":64,"regexType":"net","regex":"^2[12]\\|[^|]*\\|[^|]*\\|Voidwalker\\|3E71\\|","start":555.7,"end":560.7,"time":558.2,"lineNumber":77,"eventId":"64"},{"id":65,"regexType":"net","regex":"^2[12]\\|[^|]*\\|[^|]*\\|Voidwalker\\|(?:40B9|4659)\\|","start":565.7,"end":570.7,"time":568.2,"lineNumber":78,"eventId":"65"},{"id":66,"regexType":"net","regex":"^2[12]\\|[^|]*\\|[^|]*\\|Voidwalker\\|(?:40BA|465A)\\|","start":568.8,"end":573.8,"time":571.3,"lineNumber":79,"eventId":"66"},{"id":69,"regexType":"net","regex":"^2[12]\\|[^|]*\\|[^|]*\\|Voidwalker\\|3E71\\|","start":590.7,"end":595.7,"time":593.2,"lineNumber":82,"eventId":"69"},{"id":70,"regexType":"net","regex":"^2[12]\\|[^|]*\\|[^|]*\\|Voidwalker\\|3E71\\|","start":600,"end":605,"time":602.5,"lineNumber":83,"eventId":"70"},{"id":71,"regexType":"net","regex":"^2[12]\\|[^|]*\\|[^|]*\\|Voidwalker\\|3E71\\|","start":609.3,"end":614.3,"time":611.8,"lineNumber":84,"eventId":"71"},{"id":72,"regexType":"net","regex":"^20\\|[^|]*\\|[^|]*\\|Voidwalker\\|3E73\\|","start":-75.20000000000005,"end":629.8,"time":624.8,"lineNumber":85,"eventId":"72"}],"forceJump":[],"texts":[],"ignores":{"--Reset--":true,"--sync--":true,"Spell-In-Waiting":true}}