{"zoneId":358,"events":[{"id":"1","time":0,"name":"Start","text":"Start","activeTime":0,"lineNumber":9,"sortKey":0},{"id":"2","time":0,"name":"--sync--","text":"--sync--","activeTime":0,"lineNumber":10,"sortKey":1,"syncId":2},{"id":"3","time":5.5,"name":"Ravensclaw","text":"Ravensclaw","activeTime":0,"lineNumber":11,"sortKey":2,"syncId":3},{"id":"4","time":16.6,"name":"Ravensclaw","text":"Ravensclaw","activeTime":0,"lineNumber":12,"sortKey":3,"syncId":4},{"id":"5","time":21.8,"name":"Stardust","text":"Stardust","activeTime":0,"lineNumber":14,"duration":9,"sortKey":4,"syncId":5},{"id":"6","time":30.8,"name":"--sync--","text":"--sync--","activeTime":0,"lineNumber":15,"sortKey":5,"syncId":6},{"id":"7","time":30.9,"name":"Ravensbeak","text":"Ravensbeak","activeTime":0,"lineNumber":16,"duration":13,"sortKey":6,"syncId":7},{"id":"8","time":36.2,"name":"Raven Dive","text":"Raven Dive","activeTime":0,"lineNumber":17,"sortKey":7,"syncId":8},{"id":"9","time":40.8,"name":"Iron Chariot","text":"Iron Chariot","activeTime":0,"lineNumber":18,"sortKey":8,"syncId":9},{"id":"10","time":42.6,"name":"Thermionic Beam","text":"Thermionic Beam","activeTime":0,"lineNumber":19,"sortKey":9,"syncId":10},{"id":"11","time":43.6,"name":"Raven Dive","text":"Raven Dive","activeTime":0,"lineNumber":20,"sortKey":10,"syncId":11},{"id":"12","time":44,"name":"--sync--","text":"--sync--","activeTime":0,"lineNumber":21,"sortKey":11,"syncId":12},{"id":"13","time":48.3,"name":"Ravensclaw","text":"Ravensclaw","activeTime":0,"lineNumber":22,"sortKey":12,"syncId":13},{"id":"14","time":58.6,"name":"Stardust","text":"Stardust","activeTime":0,"lineNumber":24,"duration":9,"sortKey":13,"syncId":14},{"id":"15","time":63.4,"name":"Ravensclaw","text":"Ravensclaw","activeTime":0,"lineNumber":25,"sortKey":14,"syncId":15},{"id":"16","time":67.6,"name":"--sync--","text":"--sync--","activeTime":0,"lineNumber":26,"sortKey":15,"syncId":16},{"id":"17","time":69.4,"name":"Lunar Dynamo","text":"Lunar Dynamo","activeTime":0,"lineNumber":27,"sortKey":16,"syncId":17},{"id":"18","time":71.8,"name":"Meteor Stream","text":"Meteor Stream","activeTime":0,"lineNumber":28,"sortKey":17,"syncId":18},{"id":"19","time":74.9,"name":"Dalamud Dive","text":"Dalamud Dive","activeTime":0,"lineNumber":29,"sortKey":18,"syncId":19},{"id":"20","time":83.7,"name":"Ravensbeak","text":"Ravensbeak","activeTime":0,"lineNumber":30,"duration":13,"sortKey":19,"syncId":20},{"id":"21","time":89.5,"name":"Ravensclaw","text":"Ravensclaw","activeTime":0,"lineNumber":31,"sortKey":20,"syncId":21},{"id":"22","time":95,"name":"Stardust","text":"Stardust","activeTime":0,"lineNumber":33,"duration":9,"sortKey":21,"syncId":22},{"id":"23","time":96.6,"name":"--sync--","text":"--sync--","activeTime":0,"lineNumber":34,"sortKey":22,"syncId":23},{"id":"24","time":104,"name":"--sync--","text":"--sync--","activeTime":0,"lineNumber":35,"sortKey":23,"syncId":24},{"id":"25","time":107.2,"name":"Meteor Stream","text":"Meteor Stream","activeTime":0,"lineNumber":36,"sortKey":24},{"id":"26","time":112.3,"name":"Meteor Stream","text":"Meteor Stream","activeTime":0,"lineNumber":37,"sortKey":25},{"id":"27","time":115.4,"name":"Dalamud Dive","text":"Dalamud Dive","activeTime":0,"lineNumber":38,"sortKey":26,"syncId":27},{"id":"28","time":119.7,"name":"Ravensclaw","text":"Ravensclaw","activeTime":0,"lineNumber":39,"sortKey":27,"syncId":28},{"id":"29","time":130.2,"name":"Ravensbeak","text":"Ravensbeak","activeTime":0,"lineNumber":40,"duration":13,"sortKey":28,"syncId":29},{"id":"30","time":135.5,"name":"Stardust","text":"Stardust","activeTime":0,"lineNumber":42,"duration":9,"sortKey":29,"syncId":30},{"id":"31","time":140,"name":"Ravensclaw","text":"Ravensclaw","activeTime":0,"lineNumber":43,"sortKey":30,"syncId":31},{"id":"32","time":143.2,"name":"--sync--","text":"--sync--","activeTime":0,"lineNumber":44,"sortKey":31,"syncId":32},{"id":"33","time":144.6,"name":"--sync--","text":"--sync--","activeTime":0,"lineNumber":45,"sortKey":32,"syncId":33},{"id":"34","time":146.1,"name":"Raven Dive","text":"Raven Dive","activeTime":0,"lineNumber":46,"sortKey":33,"syncId":34},{"id":"35","time":150.7,"name":"Iron Chariot","text":"Iron Chariot","activeTime":0,"lineNumber":47,"sortKey":34,"syncId":35},{"id":"36","time":152.6,"name":"Thermionic Beam","text":"Thermionic Beam","activeTime":0,"lineNumber":48,"sortKey":35,"syncId":36},{"id":"37","time":153.6,"name":"Raven Dive","text":"Raven Dive","activeTime":0,"lineNumber":49,"sortKey":36,"syncId":37},{"id":"38","time":162.6,"name":"Ravensclaw","text":"Ravensclaw","activeTime":0,"lineNumber":50,"sortKey":37,"syncId":38},{"id":"39","time":168.6,"name":"Stardust","text":"Stardust","activeTime":0,"lineNumber":52,"duration":9,"sortKey":38,"syncId":39},{"id":"40","time":177.4,"name":"Ravensbeak","text":"Ravensbeak","activeTime":0,"lineNumber":53,"duration":13,"sortKey":39,"syncId":40},{"id":"41","time":177.7,"name":"--sync--","text":"--sync--","activeTime":0,"lineNumber":54,"sortKey":40,"syncId":41},{"id":"42","time":183.9,"name":"Lunar Dynamo","text":"Lunar Dynamo","activeTime":0,"lineNumber":55,"sortKey":41,"syncId":42},{"id":"43","time":186.2,"name":"Meteor Stream","text":"Meteor Stream","activeTime":0,"lineNumber":56,"sortKey":42,"syncId":43},{"id":"44","time":189.3,"name":"Dalamud Dive","text":"Dalamud Dive","activeTime":0,"lineNumber":57,"sortKey":43,"syncId":44},{"id":"45","time":190.4,"name":"--sync--","text":"--sync--","activeTime":0,"lineNumber":58,"sortKey":44,"syncId":45},{"id":"46","time":192.9,"name":"Ravensclaw","text":"Ravensclaw","activeTime":0,"lineNumber":59,"sortKey":45,"syncId":46},{"id":"47","time":203.9,"name":"Stardust","text":"Stardust","activeTime":0,"lineNumber":61,"duration":9,"sortKey":46,"syncId":47},{"id":"48","time":208,"name":"Ravensclaw","text":"Ravensclaw","activeTime":0,"lineNumber":62,"sortKey":47,"syncId":48},{"id":"49","time":213,"name":"--sync--","text":"--sync--","activeTime":0,"lineNumber":63,"sortKey":48,"syncId":49},{"id":"50","time":217.5,"name":"Meteor Stream","text":"Meteor Stream","activeTime":0,"lineNumber":64,"sortKey":49},{"id":"51","time":222.6,"name":"Meteor Stream","text":"Meteor Stream","activeTime":0,"lineNumber":65,"sortKey":50},{"id":"52","time":225.8,"name":"Dalamud Dive","text":"Dalamud Dive","activeTime":0,"lineNumber":66,"sortKey":51,"syncId":52},{"id":"53","time":234.2,"name":"Ravensbeak","text":"Ravensbeak","activeTime":0,"lineNumber":67,"duration":13,"sortKey":52,"syncId":53},{"id":"54","time":239.6,"name":"Ravensclaw","text":"Ravensclaw","activeTime":0,"lineNumber":68,"sortKey":53,"syncId":54},{"id":"55","time":245.8,"name":"Stardust","text":"Stardust","activeTime":0,"lineNumber":70,"duration":9,"sortKey":54,"syncId":55},{"id":"56","time":254.8,"name":"--sync--","text":"--sync--","activeTime":0,"lineNumber":71,"sortKey":55,"syncId":56},{"id":"57","time":255.5,"name":"Raven Dive","text":"Raven Dive","activeTime":0,"lineNumber":72,"sortKey":56,"syncId":57},{"id":"58","time":260.1,"name":"Iron Chariot","text":"Iron Chariot","activeTime":0,"lineNumber":73,"sortKey":57,"syncId":58},{"id":"59","time":262.1,"name":"Thermionic Beam","text":"Thermionic Beam","activeTime":0,"lineNumber":74,"sortKey":58,"syncId":59},{"id":"60","time":263.1,"name":"Raven Dive","text":"Raven Dive","activeTime":0,"lineNumber":75,"sortKey":59,"syncId":60},{"id":"61","time":266.4,"name":"Ravensclaw","text":"Ravensclaw","activeTime":0,"lineNumber":76,"sortKey":60,"syncId":61},{"id":"62","time":277.3,"name":"Ravensbeak","text":"Ravensbeak","activeTime":0,"lineNumber":77,"duration":13,"sortKey":61,"syncId":62},{"id":"63","time":283,"name":"Stardust","text":"Stardust","activeTime":0,"lineNumber":79,"duration":9,"sortKey":62,"syncId":63},{"id":"64","time":286.8,"name":"Ravensclaw","text":"Ravensclaw","activeTime":0,"lineNumber":80,"sortKey":63,"syncId":64},{"id":"65","time":292,"name":"--sync--","text":"--sync--","activeTime":0,"lineNumber":81,"sortKey":64,"syncId":65},{"id":"66","time":294.3,"name":"Lunar Dynamo","text":"Lunar Dynamo","activeTime":0,"lineNumber":82,"sortKey":65,"syncId":66},{"id":"67","time":296.7,"name":"Meteor Stream","text":"Meteor Stream","activeTime":0,"lineNumber":83,"sortKey":66,"syncId":67},{"id":"68","time":299.9,"name":"Dalamud Dive","text":"Dalamud Dive","activeTime":0,"lineNumber":84,"sortKey":67,"syncId":68},{"id":"69","time":307.9,"name":"Ravensclaw","text":"Ravensclaw","activeTime":0,"lineNumber":85,"sortKey":68,"syncId":69},{"id":"70","time":314.3,"name":"Stardust","text":"Stardust","activeTime":0,"lineNumber":87,"duration":9,"sortKey":69,"syncId":70},{"id":"71","time":322.8,"name":"Ravensbeak","text":"Ravensbeak","activeTime":0,"lineNumber":88,"sortKey":70,"syncId":71},{"id":"72","time":323.3,"name":"--sync--","text":"--sync--","activeTime":0,"lineNumber":89,"sortKey":71,"syncId":72},{"id":"73","time":332,"name":"Meteor Stream","text":"Meteor Stream","activeTime":0,"lineNumber":90,"sortKey":72,"syncId":73},{"id":"74","time":335.9,"name":"--sync--","text":"--sync--","activeTime":0,"lineNumber":91,"sortKey":73,"syncId":74},{"id":"75","time":337,"name":"Meteor Stream","text":"Meteor Stream","activeTime":0,"lineNumber":92,"sortKey":74,"syncId":75},{"id":"76","time":340.2,"name":"Dalamud Dive","text":"Dalamud Dive","activeTime":0,"lineNumber":93,"sortKey":75,"syncId":76},{"id":"77","time":343.2,"name":"Ravensclaw","text":"Ravensclaw","activeTime":0,"lineNumber":94,"sortKey":76,"syncId":77},{"id":"78","time":355,"name":"Stardust","text":"Stardust","activeTime":0,"lineNumber":96,"duration":9,"sortKey":77,"syncId":78},{"id":"79","time":358.5,"name":"Ravensclaw","text":"Ravensclaw","activeTime":0,"lineNumber":97,"sortKey":78,"syncId":79},{"id":"80","time":364,"name":"--sync--","text":"--sync--","activeTime":0,"lineNumber":98,"sortKey":79,"syncId":80},{"id":"81","time":366,"name":"Raven Dive","text":"Raven Dive","activeTime":0,"lineNumber":99,"sortKey":80,"syncId":81},{"id":"82","time":370.5,"name":"Iron Chariot","text":"Iron Chariot","activeTime":0,"lineNumber":100,"sortKey":81,"syncId":82},{"id":"83","time":372.7,"name":"Thermionic Beam","text":"Thermionic Beam","activeTime":0,"lineNumber":101,"sortKey":82,"syncId":83},{"id":"84","time":373.7,"name":"Raven Dive","text":"Raven Dive","activeTime":0,"lineNumber":102,"sortKey":83,"syncId":84},{"id":"85","time":500,"name":"--untargetable--","text":"--untargetable--","activeTime":0,"lineNumber":108,"sortKey":84},{"id":"86","time":503.3,"name":"Golem Meteors","text":"Golem Meteors","activeTime":0,"lineNumber":109,"duration":11,"sortKey":85,"syncId":86},{"id":"87","time":514.3,"name":"--sync--","text":"--sync--","activeTime":0,"lineNumber":110,"sortKey":86,"syncId":87},{"id":"88","time":582.3,"name":"Meteor 1/6","text":"Meteor 1/6","activeTime":0,"lineNumber":111,"duration":7,"sortKey":87,"syncId":88},{"id":"89","time":584.3,"name":"Meteor 2/6","text":"Meteor 2/6","activeTime":0,"lineNumber":112,"duration":7,"sortKey":88},{"id":"90","time":586.3,"name":"Meteor 3/6","text":"Meteor 3/6","activeTime":0,"lineNumber":113,"duration":7,"sortKey":89},{"id":"91","time":588.3,"name":"Meteor 4/6","text":"Meteor 4/6","activeTime":0,"lineNumber":114,"duration":7,"sortKey":90},{"id":"92","time":590.5,"name":"Meteor 5/6","text":"Meteor 5/6","activeTime":0,"lineNumber":115,"duration":7,"sortKey":91},{"id":"93","time":592.5,"name":"Meteor 6/6","text":"Meteor 6/6","activeTime":0,"lineNumber":116,"duration":7,"sortKey":92},{"id":"94","time":598.3,"name":"Golem Meteors","text":"Golem Meteors","activeTime":0,"lineNumber":117,"duration":11,"sortKey":93,"syncId":94},{"id":"95","time":609.3,"name":"--sync--","text":"--sync--","activeTime":0,"lineNumber":118,"sortKey":94,"syncId":95},{"id":"96","time":683.5,"name":"Megaflare","text":"Megaflare","activeTime":0,"lineNumber":119,"sortKey":95,"syncId":96},{"id":"97","time":693.6,"name":"Dalamud Dive","text":"Dalamud Dive","activeTime":0,"lineNumber":125,"sortKey":96,"syncId":97},{"id":"98","time":695.6,"name":"--targetable--","text":"--targetable--","activeTime":0,"lineNumber":126,"sortKey":97},{"id":"99","time":699.2,"name":"--sync--","text":"--sync--","activeTime":0,"lineNumber":128,"sortKey":98,"syncId":99},{"id":"100","time":701.9,"name":"Heavensfall","text":"Heavensfall","activeTime":0,"lineNumber":129,"sortKey":99,"syncId":100},{"id":"101","time":714.3,"name":"Bahamut's Claw x2","text":"Bahamut's Claw x2","activeTime":0,"lineNumber":130,"sortKey":100},{"id":"102","time":716,"name":"Ghost Add 1 (North)","text":"Ghost Add 1 (North)","activeTime":0,"lineNumber":131,"sortKey":101},{"id":"103","time":721.8,"name":"Binding Coil","text":"Binding Coil","activeTime":0,"lineNumber":132,"sortKey":102,"syncId":103},{"id":"104","time":737,"name":"Bahamut's Claw x2","text":"Bahamut's Claw x2","activeTime":0,"lineNumber":133,"sortKey":103},{"id":"105","time":744.4,"name":"Binding Coil","text":"Binding Coil","activeTime":0,"lineNumber":134,"sortKey":104,"syncId":105},{"id":"106","time":749.5,"name":"--sync--","text":"--sync--","activeTime":0,"lineNumber":136,"sortKey":105,"syncId":106},{"id":"107","time":752.2,"name":"Heavensfall","text":"Heavensfall","activeTime":0,"lineNumber":137,"sortKey":106,"syncId":107},{"id":"108","time":755.9,"name":"Super Nova x2","text":"Super Nova x2","activeTime":0,"lineNumber":138,"duration":2.3,"sortKey":107},{"id":"109","time":768.7,"name":"Bahamut's Claw x2","text":"Bahamut's Claw x2","activeTime":0,"lineNumber":139,"sortKey":108},{"id":"110","time":775.9,"name":"Binding Coil","text":"Binding Coil","activeTime":0,"lineNumber":140,"sortKey":109,"syncId":110},{"id":"111","time":776,"name":"Ghost Add 2 (East)","text":"Ghost Add 2 (East)","activeTime":0,"lineNumber":141,"sortKey":110},{"id":"112","time":791.3,"name":"Bahamut's Claw x2","text":"Bahamut's Claw x2","activeTime":0,"lineNumber":142,"sortKey":111},{"id":"113","time":798.5,"name":"Binding Coil","text":"Binding Coil","activeTime":0,"lineNumber":143,"sortKey":112,"syncId":113},{"id":"114","time":803.5,"name":"--sync--","text":"--sync--","activeTime":0,"lineNumber":145,"sortKey":113,"syncId":114},{"id":"115","time":806.2,"name":"Heavensfall","text":"Heavensfall","activeTime":0,"lineNumber":146,"sortKey":114,"syncId":115},{"id":"116","time":809.9,"name":"Super Nova x2","text":"Super Nova x2","activeTime":0,"lineNumber":147,"duration":2.3,"sortKey":115},{"id":"117","time":822.7,"name":"Bahamut's Claw x2","text":"Bahamut's Claw x2","activeTime":0,"lineNumber":148,"sortKey":116},{"id":"118","time":829.9,"name":"Binding Coil","text":"Binding Coil","activeTime":0,"lineNumber":149,"sortKey":117,"syncId":118},{"id":"119","time":836,"name":"Ghost Add 3 (South)","text":"Ghost Add 3 (South)","activeTime":0,"lineNumber":150,"sortKey":118},{"id":"120","time":845.3,"name":"Bahamut's Claw x2","text":"Bahamut's Claw x2","activeTime":0,"lineNumber":151,"sortKey":119},{"id":"121","time":852.5,"name":"Binding Coil","text":"Binding Coil","activeTime":0,"lineNumber":152,"sortKey":120,"syncId":121},{"id":"122","time":857.5,"name":"--sync--","text":"--sync--","activeTime":0,"lineNumber":154,"sortKey":121,"syncId":122},{"id":"123","time":860.2,"name":"Heavensfall","text":"Heavensfall","activeTime":0,"lineNumber":155,"sortKey":122,"syncId":123},{"id":"124","time":863.9,"name":"Super Nova x2","text":"Super Nova x2","activeTime":0,"lineNumber":156,"duration":2.3,"sortKey":123},{"id":"125","time":876.7,"name":"Bahamut's Claw x2","text":"Bahamut's Claw x2","activeTime":0,"lineNumber":157,"sortKey":124},{"id":"126","time":883.9,"name":"Binding Coil","text":"Binding Coil","activeTime":0,"lineNumber":158,"sortKey":125,"syncId":126},{"id":"127","time":899.3,"name":"Bahamut's Claw x2","text":"Bahamut's Claw x2","activeTime":0,"lineNumber":159,"sortKey":126},{"id":"128","time":906.5,"name":"Binding Coil","text":"Binding Coil","activeTime":0,"lineNumber":160,"sortKey":127,"syncId":128},{"id":"129","time":911.5,"name":"--sync--","text":"--sync--","activeTime":0,"lineNumber":162,"sortKey":128,"syncId":129},{"id":"130","time":914.2,"name":"Heavensfall","text":"Heavensfall","activeTime":0,"lineNumber":163,"sortKey":129},{"id":"131","time":917.9,"name":"Super Nova x2","text":"Super Nova x2","activeTime":0,"lineNumber":164,"sortKey":130},{"id":"132","time":930.7,"name":"Bahamut's Claw x2","text":"Bahamut's Claw x2","activeTime":0,"lineNumber":165,"sortKey":131},{"id":"133","time":937.9,"name":"Binding Coil","text":"Binding Coil","activeTime":0,"lineNumber":166,"sortKey":132},{"id":"134","time":953.3,"name":"Bahamut's Claw x2","text":"Bahamut's Claw x2","activeTime":0,"lineNumber":167,"sortKey":133},{"id":"135","time":960.5,"name":"Binding Coil","text":"Binding Coil","activeTime":0,"lineNumber":168,"sortKey":134},{"id":"136","time":1000,"name":"Bahamut's Favor","text":"Bahamut's Favor","activeTime":0,"lineNumber":172,"sortKey":135,"syncId":136},{"id":"137","time":1003.1,"name":"Bahamut's Claw x5","text":"Bahamut's Claw x5","activeTime":0,"lineNumber":173,"duration":2.9,"sortKey":136},{"id":"138","time":1013.9,"name":"Chain Lightning","text":"Chain Lightning","activeTime":0,"lineNumber":174,"duration":6,"sortKey":137,"syncId":138},{"id":"139","time":1014.4,"name":"Raven Dive","text":"Raven Dive","activeTime":0,"lineNumber":175,"sortKey":138,"syncId":139},{"id":"140","time":1014.9,"name":"Fireball (Out)","text":"Fireball (Out)","activeTime":0,"lineNumber":176,"sortKey":139,"syncId":140},{"id":"141","time":1019,"name":"Lunar Dynamo","text":"Lunar Dynamo","activeTime":0,"lineNumber":177,"sortKey":140,"syncId":141},{"id":"142","time":1025.9,"name":"Chain Lightning","text":"Chain Lightning","activeTime":0,"lineNumber":178,"duration":6,"sortKey":141,"syncId":142},{"id":"143","time":1026.9,"name":"Fireball (In)","text":"Fireball (In)","activeTime":0,"lineNumber":179,"sortKey":142,"syncId":143},{"id":"144","time":1038,"name":"Chain Lightning","text":"Chain Lightning","activeTime":0,"lineNumber":180,"duration":6,"sortKey":143,"syncId":144},{"id":"145","time":1039,"name":"Fireball (Out)","text":"Fireball (Out)","activeTime":0,"lineNumber":181,"sortKey":144,"syncId":145},{"id":"146","time":1040.2,"name":"Iron Chariot","text":"Iron Chariot","activeTime":0,"lineNumber":182,"sortKey":145,"syncId":146},{"id":"147","time":1041.9,"name":"Super Nova x3","text":"Super Nova x3","activeTime":0,"lineNumber":183,"duration":3,"sortKey":146},{"id":"148","time":1047.4,"name":"Thermionic Beam","text":"Thermionic Beam","activeTime":0,"lineNumber":184,"sortKey":147,"syncId":148},{"id":"149","time":1050,"name":"Chain Lightning","text":"Chain Lightning","activeTime":0,"lineNumber":185,"duration":6,"sortKey":148,"syncId":149},{"id":"150","time":1051.2,"name":"Fireball (In)","text":"Fireball (In)","activeTime":0,"lineNumber":186,"sortKey":149,"syncId":150},{"id":"151","time":1054.2,"name":"Bahamut's Claw x5","text":"Bahamut's Claw x5","activeTime":0,"lineNumber":187,"duration":2.9,"sortKey":150},{"id":"152","time":1061.2,"name":"Divebomb Mark A","text":"Divebomb Mark A","activeTime":0,"lineNumber":188,"duration":5,"sortKey":151},{"id":"153","time":1067.3,"name":"Divebomb Mark B","text":"Divebomb Mark B","activeTime":0,"lineNumber":189,"duration":5,"sortKey":152},{"id":"154","time":1070.5,"name":"Cauterize x2","text":"Cauterize x2","activeTime":0,"lineNumber":190,"sortKey":153,"syncId":154},{"id":"155","time":1070.6,"name":"Meteor Stream","text":"Meteor Stream","activeTime":0,"lineNumber":191,"sortKey":154,"syncId":155},{"id":"156","time":1076.6,"name":"Cauterize x1","text":"Cauterize x1","activeTime":0,"lineNumber":192,"sortKey":155,"syncId":156},{"id":"157","time":1076.7,"name":"Meteor Stream","text":"Meteor Stream","activeTime":0,"lineNumber":193,"sortKey":156,"syncId":157},{"id":"158","time":1080.8,"name":"Dalamud Dive","text":"Dalamud Dive","activeTime":0,"lineNumber":194,"sortKey":157,"syncId":158},{"id":"159","time":1096.6,"name":"Bahamut's Favor","text":"Bahamut's Favor","activeTime":0,"lineNumber":196,"sortKey":158,"syncId":159},{"id":"160","time":1099.7,"name":"Bahamut's Claw x5","text":"Bahamut's Claw x5","activeTime":0,"lineNumber":197,"duration":2.9,"sortKey":159},{"id":"161","time":1110.4,"name":"Raven Dive","text":"Raven Dive","activeTime":0,"lineNumber":198,"sortKey":160,"syncId":161},{"id":"162","time":1110.4,"name":"Chain Lightning","text":"Chain Lightning","activeTime":0,"lineNumber":199,"duration":6,"sortKey":161,"syncId":162},{"id":"163","time":1111.3,"name":"Fireball (Out)","text":"Fireball (Out)","activeTime":0,"lineNumber":200,"sortKey":162,"syncId":163},{"id":"164","time":1114.9,"name":"Lunar Dynamo","text":"Lunar Dynamo","activeTime":0,"lineNumber":201,"sortKey":163,"syncId":164},{"id":"165","time":1122.5,"name":"Chain Lightning","text":"Chain Lightning","activeTime":0,"lineNumber":202,"duration":6,"sortKey":164,"syncId":165},{"id":"166","time":1123.4,"name":"Fireball (In)","text":"Fireball (In)","activeTime":0,"lineNumber":203,"sortKey":165,"syncId":166},{"id":"167","time":1134.4,"name":"Chain Lightning","text":"Chain Lightning","activeTime":0,"lineNumber":204,"duration":6,"sortKey":166,"syncId":167},{"id":"168","time":1135.5,"name":"Fireball (Out)","text":"Fireball (Out)","activeTime":0,"lineNumber":205,"sortKey":167,"syncId":168},{"id":"169","time":1136,"name":"Iron Chariot","text":"Iron Chariot","activeTime":0,"lineNumber":206,"sortKey":168,"syncId":169},{"id":"170","time":1137.8,"name":"Super Nova x3","text":"Super Nova x3","activeTime":0,"lineNumber":207,"duration":3,"sortKey":169},{"id":"171","time":1143.8,"name":"Thermionic Beam","text":"Thermionic Beam","activeTime":0,"lineNumber":208,"sortKey":170,"syncId":171},{"id":"172","time":1146.6,"name":"Chain Lightning","text":"Chain Lightning","activeTime":0,"lineNumber":209,"duration":6,"sortKey":171,"syncId":172},{"id":"173","time":1147.7,"name":"Fireball (In)","text":"Fireball (In)","activeTime":0,"lineNumber":210,"sortKey":172,"syncId":173},{"id":"174","time":1150.6,"name":"Bahamut's Claw x5","text":"Bahamut's Claw x5","activeTime":0,"lineNumber":211,"duration":2.9,"sortKey":173},{"id":"175","time":1157.8,"name":"Divebomb Mark A","text":"Divebomb Mark A","activeTime":0,"lineNumber":212,"duration":5,"sortKey":174},{"id":"176","time":1163.9,"name":"Divebomb Mark B","text":"Divebomb Mark B","activeTime":0,"lineNumber":213,"duration":5,"sortKey":175},{"id":"177","time":1164.3,"name":"Iron Chariot","text":"Iron Chariot","activeTime":0,"lineNumber":214,"sortKey":176,"syncId":177},{"id":"178","time":1167.1,"name":"Cauterize x2","text":"Cauterize x2","activeTime":0,"lineNumber":215,"sortKey":177,"syncId":178},{"id":"179","time":1168.1,"name":"Raven Dive","text":"Raven Dive","activeTime":0,"lineNumber":216,"sortKey":178,"syncId":179},{"id":"180","time":1172.7,"name":"Lunar Dynamo","text":"Lunar Dynamo","activeTime":0,"lineNumber":217,"sortKey":179,"syncId":180},{"id":"181","time":1173.2,"name":"Cauterize x1","text":"Cauterize x1","activeTime":0,"lineNumber":218,"sortKey":180,"syncId":181},{"id":"182","time":1193.1,"name":"Bahamut's Favor","text":"Bahamut's Favor","activeTime":0,"lineNumber":220,"sortKey":181,"syncId":182},{"id":"183","time":1196.1,"name":"Bahamut's Claw x5","text":"Bahamut's Claw x5","activeTime":0,"lineNumber":221,"duration":2.9,"sortKey":182},{"id":"184","time":1206.9,"name":"Raven Dive","text":"Raven Dive","activeTime":0,"lineNumber":222,"sortKey":183,"syncId":184},{"id":"185","time":1207,"name":"Chain Lightning","text":"Chain Lightning","activeTime":0,"lineNumber":223,"duration":6,"sortKey":184,"syncId":185},{"id":"186","time":1207.9,"name":"Fireball (Out)","text":"Fireball (Out)","activeTime":0,"lineNumber":224,"sortKey":185,"syncId":186},{"id":"187","time":1211.4,"name":"Lunar Dynamo","text":"Lunar Dynamo","activeTime":0,"lineNumber":225,"sortKey":186,"syncId":187},{"id":"188","time":1219,"name":"Chain Lightning","text":"Chain Lightning","activeTime":0,"lineNumber":226,"duration":6,"sortKey":187,"syncId":188},{"id":"189","time":1219.9,"name":"Fireball (In)","text":"Fireball (In)","activeTime":0,"lineNumber":227,"sortKey":188,"syncId":189},{"id":"190","time":1231,"name":"Chain Lightning","text":"Chain Lightning","activeTime":0,"lineNumber":228,"duration":6,"sortKey":189,"syncId":190},{"id":"191","time":1232.1,"name":"Fireball (Out)","text":"Fireball (Out)","activeTime":0,"lineNumber":229,"sortKey":190,"syncId":191},{"id":"192","time":1232.6,"name":"Iron Chariot","text":"Iron Chariot","activeTime":0,"lineNumber":230,"sortKey":191,"syncId":192},{"id":"193","time":1234.4,"name":"Super Nova x3","text":"Super Nova x3","activeTime":0,"lineNumber":231,"duration":3,"sortKey":192},{"id":"194","time":1240.5,"name":"Thermionic Beam","text":"Thermionic Beam","activeTime":0,"lineNumber":232,"sortKey":193,"syncId":194},{"id":"195","time":1243.1,"name":"Chain Lightning","text":"Chain Lightning","activeTime":0,"lineNumber":233,"duration":6,"sortKey":194,"syncId":195},{"id":"196","time":1244.4,"name":"Fireball (In)","text":"Fireball (In)","activeTime":0,"lineNumber":234,"sortKey":195,"syncId":196},{"id":"197","time":1247.4,"name":"Bahamut's Claw x5","text":"Bahamut's Claw x5","activeTime":0,"lineNumber":235,"duration":2.9,"sortKey":196},{"id":"198","time":1254.4,"name":"Divebomb Mark A","text":"Divebomb Mark A","activeTime":0,"lineNumber":236,"duration":5,"sortKey":197},{"id":"199","time":1260.3,"name":"Divebomb Mark B","text":"Divebomb Mark B","activeTime":0,"lineNumber":237,"duration":5,"sortKey":198},{"id":"200","time":1263.7,"name":"Cauterize x2","text":"Cauterize x2","activeTime":0,"lineNumber":238,"sortKey":199,"syncId":200},{"id":"201","time":1263.8,"name":"Meteor Stream","text":"Meteor Stream","activeTime":0,"lineNumber":239,"sortKey":200,"syncId":201},{"id":"202","time":1269.6,"name":"Cauterize x1","text":"Cauterize x1","activeTime":0,"lineNumber":240,"sortKey":201,"syncId":202},{"id":"203","time":1269.9,"name":"Meteor Stream","text":"Meteor Stream","activeTime":0,"lineNumber":241,"sortKey":202,"syncId":203},{"id":"204","time":1274.5,"name":"Dalamud Dive","text":"Dalamud Dive","activeTime":0,"lineNumber":242,"sortKey":203,"syncId":204},{"id":"205","time":1289.7,"name":"Bahamut's Favor","text":"Bahamut's Favor","activeTime":0,"lineNumber":244,"sortKey":204,"syncId":205},{"id":"206","time":1292.8,"name":"Bahamut's Claw x5","text":"Bahamut's Claw x5","activeTime":0,"lineNumber":245,"sortKey":205},{"id":"207","time":1303.5,"name":"Raven Dive","text":"Raven Dive","activeTime":0,"lineNumber":246,"sortKey":206},{"id":"208","time":1303.5,"name":"Chain Lightning","text":"Chain Lightning","activeTime":0,"lineNumber":247,"sortKey":207},{"id":"209","time":1304.4,"name":"Fireball (Out)","text":"Fireball (Out)","activeTime":0,"lineNumber":248,"sortKey":208},{"id":"210","time":1308,"name":"Lunar Dynamo","text":"Lunar Dynamo","activeTime":0,"lineNumber":249,"sortKey":209},{"id":"211","time":1315.6,"name":"Chain Lightning","text":"Chain Lightning","activeTime":0,"lineNumber":250,"sortKey":210},{"id":"212","time":1316.5,"name":"Fireball (In)","text":"Fireball (In)","activeTime":0,"lineNumber":251,"sortKey":211},{"id":"213","time":1327.5,"name":"Chain Lightning","text":"Chain Lightning","activeTime":0,"lineNumber":252,"sortKey":212},{"id":"214","time":1328.6,"name":"Fireball (Out)","text":"Fireball (Out)","activeTime":0,"lineNumber":253,"sortKey":213},{"id":"215","time":1329.1,"name":"Iron Chariot","text":"Iron Chariot","activeTime":0,"lineNumber":254,"sortKey":214},{"id":"216","time":1330.9,"name":"Super Nova x3","text":"Super Nova x3","activeTime":0,"lineNumber":255,"sortKey":215},{"id":"217","time":1336.9,"name":"Thermionic Beam","text":"Thermionic Beam","activeTime":0,"lineNumber":256,"sortKey":216},{"id":"218","time":1339.7,"name":"Chain Lightning","text":"Chain Lightning","activeTime":0,"lineNumber":257,"sortKey":217},{"id":"219","time":1340.8,"name":"Fireball (In)","text":"Fireball (In)","activeTime":0,"lineNumber":258,"sortKey":218},{"id":"220","time":1343.7,"name":"Bahamut's Claw x5","text":"Bahamut's Claw x5","activeTime":0,"lineNumber":259,"sortKey":219},{"id":"221","time":1350.9,"name":"Divebomb Mark A","text":"Divebomb Mark A","activeTime":0,"lineNumber":260,"sortKey":220},{"id":"222","time":1357,"name":"Divebomb Mark B","text":"Divebomb Mark B","activeTime":0,"lineNumber":261,"sortKey":221},{"id":"223","time":1357.4,"name":"Iron Chariot","text":"Iron Chariot","activeTime":0,"lineNumber":262,"sortKey":222},{"id":"224","time":1360.2,"name":"Cauterize x2","text":"Cauterize x2","activeTime":0,"lineNumber":263,"sortKey":223},{"id":"225","time":1361.2,"name":"Raven Dive","text":"Raven Dive","activeTime":0,"lineNumber":264,"sortKey":224},{"id":"226","time":1365.8,"name":"Lunar Dynamo","text":"Lunar Dynamo","activeTime":0,"lineNumber":265,"sortKey":225},{"id":"227","time":1366.3,"name":"Cauterize x1","text":"Cauterize x1","activeTime":0,"lineNumber":266,"sortKey":226},{"id":"228","time":2000,"name":"Megaflare Enrage","text":"Megaflare Enrage","activeTime":0,"lineNumber":270,"sortKey":227,"syncId":228},{"id":"229","time":2008.5,"name":"Megaflare Enrage","text":"Megaflare Enrage","activeTime":0,"lineNumber":271,"sortKey":228},{"id":"230","time":2017,"name":"Megaflare Enrage","text":"Megaflare Enrage","activeTime":0,"lineNumber":272,"sortKey":229},{"id":"231","time":2025.5,"name":"Megaflare Enrage","text":"Megaflare Enrage","activeTime":0,"lineNumber":273,"sortKey":230},{"id":"232","time":2034,"name":"Megaflare Enrage","text":"Megaflare Enrage","activeTime":0,"lineNumber":274,"sortKey":231}],"syncStart":[{"id":96,"regexType":"net","regex":"^2[12]\\|[^|]*\\|[^|]*\\|Nael deus Darnus\\|7E7\\|","start":-16.5,"end":1383.5,"time":683.5,"lineNumber":119,"eventId":"96"},{"id":86,"regexType":"net","regex":"^27\\|[^|]*\\|[^|]*\\|[^|]*\\|(?:[^|]*\\|){2}0007\\|","start":-1.6999999999999886,"end":503.3,"time":503.3,"lineNumber":109,"eventId":"86"},{"id":3,"regexType":"net","regex":"^2[12]\\|[^|]*\\|[^|]*\\|Nael deus Darnus\\|7D5\\|","start":-0.5,"end":10.5,"time":5.5,"lineNumber":11,"eventId":"3"},{"id":100,"regexType":"net","regex":"^2[12]\\|[^|]*\\|[^|]*\\|Ragnarok\\|7E4\\|","start":-0.10000000000002274,"end":711.9,"time":701.9,"lineNumber":129,"eventId":"100"},{"id":2,"regexType":"net","regex":"^260\\|[^|]*\\|[^|]*\\|1\\|","start":0,"end":1,"time":0,"lineNumber":10,"eventId":"2"},{"id":136,"regexType":"net","regex":"^2[12]\\|[^|]*\\|[^|]*\\|Nael deus Darnus\\|7E6\\|","start":0,"end":1080,"time":1000,"lineNumber":172,"eventId":"136"},{"id":228,"regexType":"net","regex":"^2[12]\\|[^|]*\\|[^|]*\\|Nael deus Darnus\\|7E8\\|","start":0,"end":4000,"time":2000,"lineNumber":270,"eventId":"228"},{"id":4,"regexType":"net","regex":"^2[12]\\|[^|]*\\|[^|]*\\|Nael deus Darnus\\|7D5\\|","start":14.100000000000001,"end":19.1,"time":16.6,"lineNumber":12,"eventId":"4"},{"id":5,"regexType":"net","regex":"^2[12]\\|[^|]*\\|[^|]*\\|Nael deus Darnus\\|877\\|","start":19.3,"end":24.3,"time":21.8,"lineNumber":14,"eventId":"5"},{"id":6,"regexType":"net","regex":"^2[12]\\|[^|]*\\|[^|]*\\|(?:Astral Debris|Umbral Debris)\\|7E9\\|","start":28.3,"end":33.3,"time":30.8,"lineNumber":15,"eventId":"6"},{"id":7,"regexType":"net","regex":"^2[12]\\|[^|]*\\|[^|]*\\|Nael deus Darnus\\|7D6\\|","start":28.4,"end":33.4,"time":30.9,"lineNumber":16,"eventId":"7"},{"id":8,"regexType":"net","regex":"^2[12]\\|[^|]*\\|[^|]*\\|Nael deus Darnus\\|7DD\\|","start":33.7,"end":38.7,"time":36.2,"lineNumber":17,"eventId":"8"},{"id":9,"regexType":"net","regex":"^2[12]\\|[^|]*\\|[^|]*\\|Nael deus Darnus\\|7D8\\|","start":38.3,"end":43.3,"time":40.8,"lineNumber":18,"eventId":"9"},{"id":10,"regexType":"net","regex":"^2[12]\\|[^|]*\\|[^|]*\\|Nael deus Darnus\\|7DF\\|","start":40.1,"end":45.1,"time":42.6,"lineNumber":19,"eventId":"10"},{"id":11,"regexType":"net","regex":"^2[12]\\|[^|]*\\|[^|]*\\|Nael deus Darnus\\|7DD\\|","start":41.1,"end":46.1,"time":43.6,"lineNumber":20,"eventId":"11"},{"id":12,"regexType":"net","regex":"^2[12]\\|[^|]*\\|[^|]*\\|Nael deus Darnus\\|7D7\\|","start":41.5,"end":46.5,"time":44,"lineNumber":21,"eventId":"12"},{"id":13,"regexType":"net","regex":"^2[12]\\|[^|]*\\|[^|]*\\|Nael deus Darnus\\|7D5\\|","start":45.8,"end":50.8,"time":48.3,"lineNumber":22,"eventId":"13"},{"id":14,"regexType":"net","regex":"^2[12]\\|[^|]*\\|[^|]*\\|Nael deus Darnus\\|877\\|","start":56.1,"end":61.1,"time":58.6,"lineNumber":24,"eventId":"14"},{"id":15,"regexType":"net","regex":"^2[12]\\|[^|]*\\|[^|]*\\|Nael deus Darnus\\|7D5\\|","start":60.9,"end":65.9,"time":63.4,"lineNumber":25,"eventId":"15"},{"id":16,"regexType":"net","regex":"^2[12]\\|[^|]*\\|[^|]*\\|(?:Astral Debris|Umbral Debris)\\|7E9\\|","start":65.1,"end":70.1,"time":67.6,"lineNumber":26,"eventId":"16"},{"id":17,"regexType":"net","regex":"^2[12]\\|[^|]*\\|[^|]*\\|Nael deus Darnus\\|7DA\\|","start":66.9,"end":71.9,"time":69.4,"lineNumber":27,"eventId":"17"},{"id":18,"regexType":"net","regex":"^2[12]\\|[^|]*\\|[^|]*\\|Nael Geminus\\|7DE\\|","start":69.3,"end":74.3,"time":71.8,"lineNumber":28,"eventId":"18"},{"id":19,"regexType":"net","regex":"^2[12]\\|[^|]*\\|[^|]*\\|Nael deus Darnus\\|7DC\\|","start":72.4,"end":77.4,"time":74.9,"lineNumber":29,"eventId":"19"},{"id":20,"regexType":"net","regex":"^2[12]\\|[^|]*\\|[^|]*\\|Nael deus Darnus\\|7D6\\|","start":81.2,"end":86.2,"time":83.7,"lineNumber":30,"eventId":"20"},{"id":21,"regexType":"net","regex":"^2[12]\\|[^|]*\\|[^|]*\\|Nael deus Darnus\\|7D5\\|","start":87,"end":92,"time":89.5,"lineNumber":31,"eventId":"21"},{"id":22,"regexType":"net","regex":"^2[12]\\|[^|]*\\|[^|]*\\|Nael deus Darnus\\|877\\|","start":92.5,"end":97.5,"time":95,"lineNumber":33,"eventId":"22"},{"id":23,"regexType":"net","regex":"^2[12]\\|[^|]*\\|[^|]*\\|Nael deus Darnus\\|7D7\\|","start":94.1,"end":99.1,"time":96.6,"lineNumber":34,"eventId":"23"},{"id":24,"regexType":"net","regex":"^2[12]\\|[^|]*\\|[^|]*\\|(?:Astral Debris|Umbral Debris)\\|7E9\\|","start":101.5,"end":106.5,"time":104,"lineNumber":35,"eventId":"24"},{"id":27,"regexType":"net","regex":"^2[12]\\|[^|]*\\|[^|]*\\|Nael deus Darnus\\|7DC\\|","start":112.9,"end":117.9,"time":115.4,"lineNumber":38,"eventId":"27"},{"id":28,"regexType":"net","regex":"^2[12]\\|[^|]*\\|[^|]*\\|Nael deus Darnus\\|7D5\\|","start":117.2,"end":122.2,"time":119.7,"lineNumber":39,"eventId":"28"},{"id":29,"regexType":"net","regex":"^2[12]\\|[^|]*\\|[^|]*\\|Nael deus Darnus\\|7D6\\|","start":127.69999999999999,"end":132.7,"time":130.2,"lineNumber":40,"eventId":"29"},{"id":30,"regexType":"net","regex":"^2[12]\\|[^|]*\\|[^|]*\\|Nael deus Darnus\\|877\\|","start":133,"end":138,"time":135.5,"lineNumber":42,"eventId":"30"},{"id":31,"regexType":"net","regex":"^2[12]\\|[^|]*\\|[^|]*\\|Nael deus Darnus\\|7D5\\|","start":137.5,"end":142.5,"time":140,"lineNumber":43,"eventId":"31"},{"id":32,"regexType":"net","regex":"^2[12]\\|[^|]*\\|[^|]*\\|Nael deus Darnus\\|7D7\\|","start":140.7,"end":145.7,"time":143.2,"lineNumber":44,"eventId":"32"},{"id":33,"regexType":"net","regex":"^2[12]\\|[^|]*\\|[^|]*\\|(?:Astral Debris|Umbral Debris)\\|7E9\\|","start":142.1,"end":147.1,"time":144.6,"lineNumber":45,"eventId":"33"},{"id":34,"regexType":"net","regex":"^2[12]\\|[^|]*\\|[^|]*\\|Nael deus Darnus\\|7DD\\|","start":143.6,"end":148.6,"time":146.1,"lineNumber":46,"eventId":"34"},{"id":35,"regexType":"net","regex":"^2[12]\\|[^|]*\\|[^|]*\\|Nael deus Darnus\\|7D8\\|","start":148.2,"end":153.2,"time":150.7,"lineNumber":47,"eventId":"35"},{"id":36,"regexType":"net","regex":"^2[12]\\|[^|]*\\|[^|]*\\|Nael deus Darnus\\|7DF\\|","start":150.1,"end":155.1,"time":152.6,"lineNumber":48,"eventId":"36"},{"id":37,"regexType":"net","regex":"^2[12]\\|[^|]*\\|[^|]*\\|Nael deus Darnus\\|7DD\\|","start":151.1,"end":156.1,"time":153.6,"lineNumber":49,"eventId":"37"},{"id":38,"regexType":"net","regex":"^2[12]\\|[^|]*\\|[^|]*\\|Nael deus Darnus\\|7D5\\|","start":160.1,"end":165.1,"time":162.6,"lineNumber":50,"eventId":"38"},{"id":39,"regexType":"net","regex":"^2[12]\\|[^|]*\\|[^|]*\\|Nael deus Darnus\\|877\\|","start":166.1,"end":171.1,"time":168.6,"lineNumber":52,"eventId":"39"},{"id":40,"regexType":"net","regex":"^2[12]\\|[^|]*\\|[^|]*\\|Nael deus Darnus\\|7D6\\|","start":174.9,"end":179.9,"time":177.4,"lineNumber":53,"eventId":"40"},{"id":41,"regexType":"net","regex":"^2[12]\\|[^|]*\\|[^|]*\\|(?:Astral Debris|Umbral Debris)\\|7E9\\|","start":175.2,"end":180.2,"time":177.7,"lineNumber":54,"eventId":"41"},{"id":42,"regexType":"net","regex":"^2[12]\\|[^|]*\\|[^|]*\\|Nael deus Darnus\\|7DA\\|","start":181.4,"end":186.4,"time":183.9,"lineNumber":55,"eventId":"42"},{"id":43,"regexType":"net","regex":"^2[12]\\|[^|]*\\|[^|]*\\|Nael Geminus\\|7DE\\|","start":183.7,"end":188.7,"time":186.2,"lineNumber":56,"eventId":"43"},{"id":44,"regexType":"net","regex":"^2[12]\\|[^|]*\\|[^|]*\\|Nael deus Darnus\\|7DC\\|","start":186.8,"end":191.8,"time":189.3,"lineNumber":57,"eventId":"44"},{"id":45,"regexType":"net","regex":"^2[12]\\|[^|]*\\|[^|]*\\|Nael deus Darnus\\|7D7\\|","start":187.9,"end":192.9,"time":190.4,"lineNumber":58,"eventId":"45"},{"id":46,"regexType":"net","regex":"^2[12]\\|[^|]*\\|[^|]*\\|Nael deus Darnus\\|7D5\\|","start":190.4,"end":195.4,"time":192.9,"lineNumber":59,"eventId":"46"},{"id":47,"regexType":"net","regex":"^2[12]\\|[^|]*\\|[^|]*\\|Nael deus Darnus\\|877\\|","start":201.4,"end":206.4,"time":203.9,"lineNumber":61,"eventId":"47"},{"id":48,"regexType":"net","regex":"^2[12]\\|[^|]*\\|[^|]*\\|Nael deus Darnus\\|7D5\\|","start":205.5,"end":210.5,"time":208,"lineNumber":62,"eventId":"48"},{"id":49,"regexType":"net","regex":"^2[12]\\|[^|]*\\|[^|]*\\|(?:Astral Debris|Umbral Debris)\\|7E9\\|","start":210.5,"end":215.5,"time":213,"lineNumber":63,"eventId":"49"},{"id":52,"regexType":"net","regex":"^2[12]\\|[^|]*\\|[^|]*\\|Nael deus Darnus\\|7DC\\|","start":223.3,"end":228.3,"time":225.8,"lineNumber":66,"eventId":"52"},{"id":53,"regexType":"net","regex":"^2[12]\\|[^|]*\\|[^|]*\\|Nael deus Darnus\\|7D6\\|","start":231.7,"end":236.7,"time":234.2,"lineNumber":67,"eventId":"53"},{"id":54,"regexType":"net","regex":"^2[12]\\|[^|]*\\|[^|]*\\|Nael deus Darnus\\|7D5\\|","start":237.1,"end":242.1,"time":239.6,"lineNumber":68,"eventId":"54"},{"id":55,"regexType":"net","regex":"^2[12]\\|[^|]*\\|[^|]*\\|Nael deus Darnus\\|877\\|","start":243.3,"end":248.3,"time":245.8,"lineNumber":70,"eventId":"55"},{"id":56,"regexType":"net","regex":"^2[12]\\|[^|]*\\|[^|]*\\|(?:Astral Debris|Umbral Debris)\\|7E9\\|","start":252.3,"end":257.3,"time":254.8,"lineNumber":71,"eventId":"56"},{"id":57,"regexType":"net","regex":"^2[12]\\|[^|]*\\|[^|]*\\|Nael deus Darnus\\|7DD\\|","start":253,"end":258,"time":255.5,"lineNumber":72,"eventId":"57"},{"id":58,"regexType":"net","regex":"^2[12]\\|[^|]*\\|[^|]*\\|Nael deus Darnus\\|7D8\\|","start":257.6,"end":262.6,"time":260.1,"lineNumber":73,"eventId":"58"},{"id":59,"regexType":"net","regex":"^2[12]\\|[^|]*\\|[^|]*\\|Nael deus Darnus\\|7DF\\|","start":259.6,"end":264.6,"time":262.1,"lineNumber":74,"eventId":"59"},{"id":60,"regexType":"net","regex":"^2[12]\\|[^|]*\\|[^|]*\\|Nael deus Darnus\\|7DD\\|","start":260.6,"end":265.6,"time":263.1,"lineNumber":75,"eventId":"60"},{"id":61,"regexType":"net","regex":"^2[12]\\|[^|]*\\|[^|]*\\|Nael deus Darnus\\|7D5\\|","start":263.9,"end":268.9,"time":266.4,"lineNumber":76,"eventId":"61"},{"id":62,"regexType":"net","regex":"^2[12]\\|[^|]*\\|[^|]*\\|Nael deus Darnus\\|7D6\\|","start":274.8,"end":279.8,"time":277.3,"lineNumber":77,"eventId":"62"},{"id":63,"regexType":"net","regex":"^2[12]\\|[^|]*\\|[^|]*\\|Nael deus Darnus\\|877\\|","start":280.5,"end":285.5,"time":283,"lineNumber":79,"eventId":"63"},{"id":64,"regexType":"net","regex":"^2[12]\\|[^|]*\\|[^|]*\\|Nael deus Darnus\\|7D5\\|","start":284.3,"end":289.3,"time":286.8,"lineNumber":80,"eventId":"64"},{"id":65,"regexType":"net","regex":"^2[12]\\|[^|]*\\|[^|]*\\|(?:Astral Debris|Umbral Debris)\\|7E9\\|","start":289.5,"end":294.5,"time":292,"lineNumber":81,"eventId":"65"},{"id":66,"regexType":"net","regex":"^2[12]\\|[^|]*\\|[^|]*\\|Nael deus Darnus\\|7DA\\|","start":291.8,"end":296.8,"time":294.3,"lineNumber":82,"eventId":"66"},{"id":67,"regexType":"net","regex":"^2[12]\\|[^|]*\\|[^|]*\\|Nael Geminus\\|7DE\\|","start":294.2,"end":299.2,"time":296.7,"lineNumber":83,"eventId":"67"},{"id":68,"regexType":"net","regex":"^2[12]\\|[^|]*\\|[^|]*\\|Nael deus Darnus\\|7DC\\|","start":297.4,"end":302.4,"time":299.9,"lineNumber":84,"eventId":"68"},{"id":69,"regexType":"net","regex":"^2[12]\\|[^|]*\\|[^|]*\\|Nael deus Darnus\\|7D5\\|","start":305.4,"end":310.4,"time":307.9,"lineNumber":85,"eventId":"69"},{"id":70,"regexType":"net","regex":"^2[12]\\|[^|]*\\|[^|]*\\|Nael deus Darnus\\|877\\|","start":311.8,"end":316.8,"time":314.3,"lineNumber":87,"eventId":"70"},{"id":71,"regexType":"net","regex":"^2[12]\\|[^|]*\\|[^|]*\\|Nael deus Darnus\\|7D6\\|","start":320.3,"end":325.3,"time":322.8,"lineNumber":88,"eventId":"71"},{"id":72,"regexType":"net","regex":"^2[12]\\|[^|]*\\|[^|]*\\|(?:Astral Debris|Umbral Debris)\\|7E9\\|","start":320.8,"end":325.8,"time":323.3,"lineNumber":89,"eventId":"72"},{"id":73,"regexType":"net","regex":"^2[12]\\|[^|]*\\|[^|]*\\|Nael Geminus\\|7DE\\|","start":329.5,"end":334.5,"time":332,"lineNumber":90,"eventId":"73"},{"id":74,"regexType":"net","regex":"^2[12]\\|[^|]*\\|[^|]*\\|Nael deus Darnus\\|7D7\\|","start":333.4,"end":338.4,"time":335.9,"lineNumber":91,"eventId":"74"},{"id":75,"regexType":"net","regex":"^2[12]\\|[^|]*\\|[^|]*\\|Nael Geminus\\|7DE\\|","start":334.5,"end":339.5,"time":337,"lineNumber":92,"eventId":"75"},{"id":76,"regexType":"net","regex":"^2[12]\\|[^|]*\\|[^|]*\\|Nael deus Darnus\\|7DC\\|","start":337.7,"end":342.7,"time":340.2,"lineNumber":93,"eventId":"76"},{"id":77,"regexType":"net","regex":"^2[12]\\|[^|]*\\|[^|]*\\|Nael deus Darnus\\|7D5\\|","start":340.7,"end":345.7,"time":343.2,"lineNumber":94,"eventId":"77"},{"id":78,"regexType":"net","regex":"^2[12]\\|[^|]*\\|[^|]*\\|Nael deus Darnus\\|877\\|","start":352.5,"end":357.5,"time":355,"lineNumber":96,"eventId":"78"},{"id":79,"regexType":"net","regex":"^2[12]\\|[^|]*\\|[^|]*\\|Nael deus Darnus\\|7D5\\|","start":356,"end":361,"time":358.5,"lineNumber":97,"eventId":"79"},{"id":80,"regexType":"net","regex":"^2[12]\\|[^|]*\\|[^|]*\\|(?:Astral Debris|Umbral Debris)\\|7E9\\|","start":361.5,"end":366.5,"time":364,"lineNumber":98,"eventId":"80"},{"id":81,"regexType":"net","regex":"^2[12]\\|[^|]*\\|[^|]*\\|Nael deus Darnus\\|7DD\\|","start":363.5,"end":368.5,"time":366,"lineNumber":99,"eventId":"81"},{"id":82,"regexType":"net","regex":"^2[12]\\|[^|]*\\|[^|]*\\|Nael deus Darnus\\|7D8\\|","start":368,"end":373,"time":370.5,"lineNumber":100,"eventId":"82"},{"id":83,"regexType":"net","regex":"^2[12]\\|[^|]*\\|[^|]*\\|Nael deus Darnus\\|7DF\\|","start":370.2,"end":375.2,"time":372.7,"lineNumber":101,"eventId":"83"},{"id":84,"regexType":"net","regex":"^2[12]\\|[^|]*\\|[^|]*\\|Nael deus Darnus\\|7DD\\|","start":371.2,"end":376.2,"time":373.7,"lineNumber":102,"eventId":"84"},{"id":97,"regexType":"net","regex":"^2[12]\\|[^|]*\\|[^|]*\\|Nael deus Darnus\\|7DC\\|","start":393.6,"end":993.6,"time":693.6,"lineNumber":125,"eventId":"97"},{"id":88,"regexType":"net","regex":"^27\\|[^|]*\\|[^|]*\\|[^|]*\\|(?:[^|]*\\|){2}000[9A]\\|","start":499.29999999999995,"end":582.3,"time":582.3,"lineNumber":111,"eventId":"88"},{"id":87,"regexType":"net","regex":"^2[12]\\|[^|]*\\|[^|]*\\|Dalamud Fragment\\|7EB\\|","start":511.79999999999995,"end":516.8,"time":514.3,"lineNumber":110,"eventId":"87"},{"id":94,"regexType":"net","regex":"^27\\|[^|]*\\|[^|]*\\|[^|]*\\|(?:[^|]*\\|){2}0007\\|","start":518.3,"end":678.3,"time":598.3,"lineNumber":117,"eventId":"94"},{"id":95,"regexType":"net","regex":"^2[12]\\|[^|]*\\|[^|]*\\|Dalamud Fragment\\|7EB\\|","start":606.8,"end":611.8,"time":609.3,"lineNumber":118,"eventId":"95"},{"id":99,"regexType":"net","regex":"^2[12]\\|[^|]*\\|[^|]*\\|Nael deus Darnus\\|83B\\|","start":696.7,"end":701.7,"time":699.2,"lineNumber":128,"eventId":"99"},{"id":107,"regexType":"net","regex":"^2[12]\\|[^|]*\\|[^|]*\\|Ragnarok\\|7E4\\|","start":712.2,"end":792.2,"time":752.2,"lineNumber":137,"eventId":"107"},{"id":103,"regexType":"net","regex":"^2[12]\\|[^|]*\\|[^|]*\\|Nael deus Darnus\\|7E2\\|","start":719.3,"end":724.3,"time":721.8,"lineNumber":132,"eventId":"103"},{"id":105,"regexType":"net","regex":"^2[12]\\|[^|]*\\|[^|]*\\|Nael deus Darnus\\|7E2\\|","start":741.9,"end":746.9,"time":744.4,"lineNumber":134,"eventId":"105"},{"id":106,"regexType":"net","regex":"^2[12]\\|[^|]*\\|[^|]*\\|Nael deus Darnus\\|83B\\|","start":747,"end":752,"time":749.5,"lineNumber":136,"eventId":"106"},{"id":115,"regexType":"net","regex":"^2[12]\\|[^|]*\\|[^|]*\\|Ragnarok\\|7E4\\|","start":766.2,"end":846.2,"time":806.2,"lineNumber":146,"eventId":"115"},{"id":110,"regexType":"net","regex":"^2[12]\\|[^|]*\\|[^|]*\\|Nael deus Darnus\\|7E2\\|","start":773.4,"end":778.4,"time":775.9,"lineNumber":140,"eventId":"110"},{"id":113,"regexType":"net","regex":"^2[12]\\|[^|]*\\|[^|]*\\|Nael deus Darnus\\|7E2\\|","start":796,"end":801,"time":798.5,"lineNumber":143,"eventId":"113"},{"id":114,"regexType":"net","regex":"^2[12]\\|[^|]*\\|[^|]*\\|Nael deus Darnus\\|83B\\|","start":801,"end":806,"time":803.5,"lineNumber":145,"eventId":"114"},{"id":123,"regexType":"net","regex":"^2[12]\\|[^|]*\\|[^|]*\\|Ragnarok\\|7E4\\|","start":820.2,"end":900.2,"time":860.2,"lineNumber":155,"eventId":"123"},{"id":118,"regexType":"net","regex":"^2[12]\\|[^|]*\\|[^|]*\\|Nael deus Darnus\\|7E2\\|","start":827.4,"end":832.4,"time":829.9,"lineNumber":149,"eventId":"118"},{"id":121,"regexType":"net","regex":"^2[12]\\|[^|]*\\|[^|]*\\|Nael deus Darnus\\|7E2\\|","start":850,"end":855,"time":852.5,"lineNumber":152,"eventId":"121"},{"id":122,"regexType":"net","regex":"^2[12]\\|[^|]*\\|[^|]*\\|Nael deus Darnus\\|83B\\|","start":855,"end":860,"time":857.5,"lineNumber":154,"eventId":"122"},{"id":129,"regexType":"net","regex":"^2[12]\\|[^|]*\\|[^|]*\\|Nael deus Darnus\\|83B\\|","start":871.5,"end":951.5,"time":911.5,"lineNumber":162,"eventId":"129","jump":857.5,"jumpType":"normal"},{"id":126,"regexType":"net","regex":"^2[12]\\|[^|]*\\|[^|]*\\|Nael deus Darnus\\|7E2\\|","start":881.4,"end":886.4,"time":883.9,"lineNumber":158,"eventId":"126"},{"id":128,"regexType":"net","regex":"^2[12]\\|[^|]*\\|[^|]*\\|Nael deus Darnus\\|7E2\\|","start":904,"end":909,"time":906.5,"lineNumber":160,"eventId":"128"},{"id":138,"regexType":"net","regex":"^2[12]\\|[^|]*\\|[^|]*\\|Thunderwing\\|7FD\\|","start":1011.4,"end":1016.4,"time":1013.9,"lineNumber":174,"eventId":"138"},{"id":139,"regexType":"net","regex":"^2[12]\\|[^|]*\\|[^|]*\\|Nael deus Darnus\\|7DD\\|","start":1011.9,"end":1016.9,"time":1014.4,"lineNumber":175,"eventId":"139"},{"id":140,"regexType":"net","regex":"^2[12]\\|[^|]*\\|[^|]*\\|Firehorn\\|7FB\\|","start":1012.4,"end":1017.4,"time":1014.9,"lineNumber":176,"eventId":"140"},{"id":141,"regexType":"net","regex":"^2[12]\\|[^|]*\\|[^|]*\\|Nael deus Darnus\\|7DA\\|","start":1016.5,"end":1021.5,"time":1019,"lineNumber":177,"eventId":"141"},{"id":159,"regexType":"net","regex":"^2[12]\\|[^|]*\\|[^|]*\\|Nael deus Darnus\\|7E6\\|","start":1016.5999999999999,"end":1176.6,"time":1096.6,"lineNumber":196,"eventId":"159"},{"id":142,"regexType":"net","regex":"^2[12]\\|[^|]*\\|[^|]*\\|Thunderwing\\|7FD\\|","start":1023.4000000000001,"end":1028.4,"time":1025.9,"lineNumber":178,"eventId":"142"},{"id":143,"regexType":"net","regex":"^2[12]\\|[^|]*\\|[^|]*\\|Firehorn\\|7FB\\|","start":1024.4,"end":1029.4,"time":1026.9,"lineNumber":179,"eventId":"143"},{"id":144,"regexType":"net","regex":"^2[12]\\|[^|]*\\|[^|]*\\|Thunderwing\\|7FD\\|","start":1035.5,"end":1040.5,"time":1038,"lineNumber":180,"eventId":"144"},{"id":145,"regexType":"net","regex":"^2[12]\\|[^|]*\\|[^|]*\\|Firehorn\\|7FB\\|","start":1036.5,"end":1041.5,"time":1039,"lineNumber":181,"eventId":"145"},{"id":146,"regexType":"net","regex":"^2[12]\\|[^|]*\\|[^|]*\\|Nael deus Darnus\\|7D8\\|","start":1037.7,"end":1042.7,"time":1040.2,"lineNumber":182,"eventId":"146"},{"id":148,"regexType":"net","regex":"^2[12]\\|[^|]*\\|[^|]*\\|Nael deus Darnus\\|7DF\\|","start":1044.9,"end":1049.9,"time":1047.4,"lineNumber":184,"eventId":"148"},{"id":149,"regexType":"net","regex":"^2[12]\\|[^|]*\\|[^|]*\\|Thunderwing\\|7FD\\|","start":1047.5,"end":1052.5,"time":1050,"lineNumber":185,"eventId":"149"},{"id":150,"regexType":"net","regex":"^2[12]\\|[^|]*\\|[^|]*\\|Firehorn\\|7FB\\|","start":1048.7,"end":1053.7,"time":1051.2,"lineNumber":186,"eventId":"150"},{"id":154,"regexType":"net","regex":"^2[12]\\|[^|]*\\|[^|]*\\|Thunderwing\\|801\\|","start":1068,"end":1073,"time":1070.5,"lineNumber":190,"eventId":"154"},{"id":155,"regexType":"net","regex":"^2[12]\\|[^|]*\\|[^|]*\\|Nael Geminus\\|7DE\\|","start":1068.1,"end":1073.1,"time":1070.6,"lineNumber":191,"eventId":"155"},{"id":156,"regexType":"net","regex":"^2[12]\\|[^|]*\\|[^|]*\\|Firehorn\\|7FF\\|","start":1074.1,"end":1079.1,"time":1076.6,"lineNumber":192,"eventId":"156"},{"id":157,"regexType":"net","regex":"^2[12]\\|[^|]*\\|[^|]*\\|Nael Geminus\\|7DE\\|","start":1074.2,"end":1079.2,"time":1076.7,"lineNumber":193,"eventId":"157"},{"id":158,"regexType":"net","regex":"^2[12]\\|[^|]*\\|[^|]*\\|Nael deus Darnus\\|7DC\\|","start":1078.3,"end":1083.3,"time":1080.8,"lineNumber":194,"eventId":"158"},{"id":161,"regexType":"net","regex":"^2[12]\\|[^|]*\\|[^|]*\\|Nael deus Darnus\\|7DD\\|","start":1107.9,"end":1112.9,"time":1110.4,"lineNumber":198,"eventId":"161"},{"id":162,"regexType":"net","regex":"^2[12]\\|[^|]*\\|[^|]*\\|Thunderwing\\|7FD\\|","start":1107.9,"end":1112.9,"time":1110.4,"lineNumber":199,"eventId":"162"},{"id":163,"regexType":"net","regex":"^2[12]\\|[^|]*\\|[^|]*\\|Firehorn\\|7FB\\|","start":1108.8,"end":1113.8,"time":1111.3,"lineNumber":200,"eventId":"163"},{"id":164,"regexType":"net","regex":"^2[12]\\|[^|]*\\|[^|]*\\|Nael deus Darnus\\|7DA\\|","start":1112.4,"end":1117.4,"time":1114.9,"lineNumber":201,"eventId":"164"},{"id":182,"regexType":"net","regex":"^2[12]\\|[^|]*\\|[^|]*\\|Nael deus Darnus\\|7E6\\|","start":1113.1,"end":1273.1,"time":1193.1,"lineNumber":220,"eventId":"182"},{"id":165,"regexType":"net","regex":"^2[12]\\|[^|]*\\|[^|]*\\|Thunderwing\\|7FD\\|","start":1120,"end":1125,"time":1122.5,"lineNumber":202,"eventId":"165"},{"id":166,"regexType":"net","regex":"^2[12]\\|[^|]*\\|[^|]*\\|Firehorn\\|7FB\\|","start":1120.9,"end":1125.9,"time":1123.4,"lineNumber":203,"eventId":"166"},{"id":167,"regexType":"net","regex":"^2[12]\\|[^|]*\\|[^|]*\\|Thunderwing\\|7FD\\|","start":1131.9,"end":1136.9,"time":1134.4,"lineNumber":204,"eventId":"167"},{"id":168,"regexType":"net","regex":"^2[12]\\|[^|]*\\|[^|]*\\|Firehorn\\|7FB\\|","start":1133,"end":1138,"time":1135.5,"lineNumber":205,"eventId":"168"},{"id":169,"regexType":"net","regex":"^2[12]\\|[^|]*\\|[^|]*\\|Nael deus Darnus\\|7D8\\|","start":1133.5,"end":1138.5,"time":1136,"lineNumber":206,"eventId":"169"},{"id":171,"regexType":"net","regex":"^2[12]\\|[^|]*\\|[^|]*\\|Nael deus Darnus\\|7DF\\|","start":1141.3,"end":1146.3,"time":1143.8,"lineNumber":208,"eventId":"171"},{"id":172,"regexType":"net","regex":"^2[12]\\|[^|]*\\|[^|]*\\|Thunderwing\\|7FD\\|","start":1144.1,"end":1149.1,"time":1146.6,"lineNumber":209,"eventId":"172"},{"id":173,"regexType":"net","regex":"^2[12]\\|[^|]*\\|[^|]*\\|Firehorn\\|7FB\\|","start":1145.2,"end":1150.2,"time":1147.7,"lineNumber":210,"eventId":"173"},{"id":177,"regexType":"net","regex":"^2[12]\\|[^|]*\\|[^|]*\\|Nael deus Darnus\\|7D8\\|","start":1161.8,"end":1166.8,"time":1164.3,"lineNumber":214,"eventId":"177"},{"id":178,"regexType":"net","regex":"^2[12]\\|[^|]*\\|[^|]*\\|Firehorn\\|7FF\\|","start":1164.6,"end":1169.6,"time":1167.1,"lineNumber":215,"eventId":"178"},{"id":179,"regexType":"net","regex":"^2[12]\\|[^|]*\\|[^|]*\\|Nael deus Darnus\\|7DD\\|","start":1165.6,"end":1170.6,"time":1168.1,"lineNumber":216,"eventId":"179"},{"id":180,"regexType":"net","regex":"^2[12]\\|[^|]*\\|[^|]*\\|Nael deus Darnus\\|7DA\\|","start":1170.2,"end":1175.2,"time":1172.7,"lineNumber":217,"eventId":"180"},{"id":181,"regexType":"net","regex":"^2[12]\\|[^|]*\\|[^|]*\\|Iceclaw\\|800\\|","start":1170.7,"end":1175.7,"time":1173.2,"lineNumber":218,"eventId":"181"},{"id":184,"regexType":"net","regex":"^2[12]\\|[^|]*\\|[^|]*\\|Nael deus Darnus\\|7DD\\|","start":1204.4,"end":1209.4,"time":1206.9,"lineNumber":222,"eventId":"184"},{"id":185,"regexType":"net","regex":"^2[12]\\|[^|]*\\|[^|]*\\|Thunderwing\\|7FD\\|","start":1204.5,"end":1209.5,"time":1207,"lineNumber":223,"eventId":"185"},{"id":186,"regexType":"net","regex":"^2[12]\\|[^|]*\\|[^|]*\\|Firehorn\\|7FB\\|","start":1205.4,"end":1210.4,"time":1207.9,"lineNumber":224,"eventId":"186"},{"id":187,"regexType":"net","regex":"^2[12]\\|[^|]*\\|[^|]*\\|Nael deus Darnus\\|7DA\\|","start":1208.9,"end":1213.9,"time":1211.4,"lineNumber":225,"eventId":"187"},{"id":205,"regexType":"net","regex":"^2[12]\\|[^|]*\\|[^|]*\\|Nael deus Darnus\\|7E6\\|","start":1209.7,"end":2089.7,"time":1289.7,"lineNumber":244,"eventId":"205","jump":1096.6,"jumpType":"normal"},{"id":188,"regexType":"net","regex":"^2[12]\\|[^|]*\\|[^|]*\\|Thunderwing\\|7FD\\|","start":1216.5,"end":1221.5,"time":1219,"lineNumber":226,"eventId":"188"},{"id":189,"regexType":"net","regex":"^2[12]\\|[^|]*\\|[^|]*\\|Firehorn\\|7FB\\|","start":1217.4,"end":1222.4,"time":1219.9,"lineNumber":227,"eventId":"189"},{"id":190,"regexType":"net","regex":"^2[12]\\|[^|]*\\|[^|]*\\|Thunderwing\\|7FD\\|","start":1228.5,"end":1233.5,"time":1231,"lineNumber":228,"eventId":"190"},{"id":191,"regexType":"net","regex":"^2[12]\\|[^|]*\\|[^|]*\\|Firehorn\\|7FB\\|","start":1229.6,"end":1234.6,"time":1232.1,"lineNumber":229,"eventId":"191"},{"id":192,"regexType":"net","regex":"^2[12]\\|[^|]*\\|[^|]*\\|Nael deus Darnus\\|7D8\\|","start":1230.1,"end":1235.1,"time":1232.6,"lineNumber":230,"eventId":"192"},{"id":194,"regexType":"net","regex":"^2[12]\\|[^|]*\\|[^|]*\\|Nael deus Darnus\\|7DF\\|","start":1238,"end":1243,"time":1240.5,"lineNumber":232,"eventId":"194"},{"id":195,"regexType":"net","regex":"^2[12]\\|[^|]*\\|[^|]*\\|Thunderwing\\|7FD\\|","start":1240.6,"end":1245.6,"time":1243.1,"lineNumber":233,"eventId":"195"},{"id":196,"regexType":"net","regex":"^2[12]\\|[^|]*\\|[^|]*\\|Firehorn\\|7FB\\|","start":1241.9,"end":1246.9,"time":1244.4,"lineNumber":234,"eventId":"196"},{"id":200,"regexType":"net","regex":"^2[12]\\|[^|]*\\|[^|]*\\|Thunderwing\\|801\\|","start":1261.2,"end":1266.2,"time":1263.7,"lineNumber":238,"eventId":"200"},{"id":201,"regexType":"net","regex":"^2[12]\\|[^|]*\\|[^|]*\\|Nael Geminus\\|7DE\\|","start":1261.3,"end":1266.3,"time":1263.8,"lineNumber":239,"eventId":"201"},{"id":202,"regexType":"net","regex":"^2[12]\\|[^|]*\\|[^|]*\\|Firehorn\\|7FF\\|","start":1267.1,"end":1272.1,"time":1269.6,"lineNumber":240,"eventId":"202"},{"id":203,"regexType":"net","regex":"^2[12]\\|[^|]*\\|[^|]*\\|Nael Geminus\\|7DE\\|","start":1267.4,"end":1272.4,"time":1269.9,"lineNumber":241,"eventId":"203"},{"id":204,"regexType":"net","regex":"^2[12]\\|[^|]*\\|[^|]*\\|Nael deus Darnus\\|7DC\\|","start":1272,"end":1277,"time":1274.5,"lineNumber":242,"eventId":"204"}],"syncEnd":[{"id":2,"regexType":"net","regex":"^260\\|[^|]*\\|[^|]*\\|1\\|","start":0,"end":1,"time":0,"lineNumber":10,"eventId":"2"},{"id":3,"regexType":"net","regex":"^2[12]\\|[^|]*\\|[^|]*\\|Nael deus Darnus\\|7D5\\|","start":-0.5,"end":10.5,"time":5.5,"lineNumber":11,"eventId":"3"},{"id":4,"regexType":"net","regex":"^2[12]\\|[^|]*\\|[^|]*\\|Nael deus Darnus\\|7D5\\|","start":14.100000000000001,"end":19.1,"time":16.6,"lineNumber":12,"eventId":"4"},{"id":5,"regexType":"net","regex":"^2[12]\\|[^|]*\\|[^|]*\\|Nael deus Darnus\\|877\\|","start":19.3,"end":24.3,"time":21.8,"lineNumber":14,"eventId":"5"},{"id":6,"regexType":"net","regex":"^2[12]\\|[^|]*\\|[^|]*\\|(?:Astral Debris|Umbral Debris)\\|7E9\\|","start":28.3,"end":33.3,"time":30.8,"lineNumber":15,"eventId":"6"},{"id":7,"regexType":"net","regex":"^2[12]\\|[^|]*\\|[^|]*\\|Nael deus Darnus\\|7D6\\|","start":28.4,"end":33.4,"time":30.9,"lineNumber":16,"eventId":"7"},{"id":8,"regexType":"net","regex":"^2[12]\\|[^|]*\\|[^|]*\\|Nael deus Darnus\\|7DD\\|","start":33.7,"end":38.7,"time":36.2,"lineNumber":17,"eventId":"8"},{"id":9,"regexType":"net","regex":"^2[12]\\|[^|]*\\|[^|]*\\|Nael deus Darnus\\|7D8\\|","start":38.3,"end":43.3,"time":40.8,"lineNumber":18,"eventId":"9"},{"id":10,"regexType":"net","regex":"^2[12]\\|[^|]*\\|[^|]*\\|Nael deus Darnus\\|7DF\\|","start":40.1,"end":45.1,"time":42.6,"lineNumber":19,"eventId":"10"},{"id":11,"regexType":"net","regex":"^2[12]\\|[^|]*\\|[^|]*\\|Nael deus Darnus\\|7DD\\|","start":41.1,"end":46.1,"time":43.6,"lineNumber":20,"eventId":"11"},{"id":12,"regexType":"net","regex":"^2[12]\\|[^|]*\\|[^|]*\\|Nael deus Darnus\\|7D7\\|","start":41.5,"end":46.5,"time":44,"lineNumber":21,"eventId":"12"},{"id":13,"regexType":"net","regex":"^2[12]\\|[^|]*\\|[^|]*\\|Nael deus Darnus\\|7D5\\|","start":45.8,"end":50.8,"time":48.3,"lineNumber":22,"eventId":"13"},{"id":14,"regexType":"net","regex":"^2[12]\\|[^|]*\\|[^|]*\\|Nael deus Darnus\\|877\\|","start":56.1,"end":61.1,"time":58.6,"lineNumber":24,"eventId":"14"},{"id":15,"regexType":"net","regex":"^2[12]\\|[^|]*\\|[^|]*\\|Nael deus Darnus\\|7D5\\|","start":60.9,"end":65.9,"time":63.4,"lineNumber":25,"eventId":"15"},{"id":16,"regexType":"net","regex":"^2[12]\\|[^|]*\\|[^|]*\\|(?:Astral Debris|Umbral Debris)\\|7E9\\|","start":65.1,"end":70.1,"time":67.6,"lineNumber":26,"eventId":"16"},{"id":17,"regexType":"net","regex":"^2[12]\\|[^|]*\\|[^|]*\\|Nael deus Darnus\\|7DA\\|","start":66.9,"end":71.9,"time":69.4,"lineNumber":27,"eventId":"17"},{"id":18,"regexType":"net","regex":"^2[12]\\|[^|]*\\|[^|]*\\|Nael Geminus\\|7DE\\|","start":69.3,"end":74.3,"time":71.8,"lineNumber":28,"eventId":"18"},{"id":19,"regexType":"net","regex":"^2[12]\\|[^|]*\\|[^|]*\\|Nael deus Darnus\\|7DC\\|","start":72.4,"end":77.4,"time":74.9,"lineNumber":29,"eventId":"19"},{"id":20,"regexType":"net","regex":"^2[12]\\|[^|]*\\|[^|]*\\|Nael deus Darnus\\|7D6\\|","start":81.2,"end":86.2,"time":83.7,"lineNumber":30,"eventId":"20"},{"id":21,"regexType":"net","regex":"^2[12]\\|[^|]*\\|[^|]*\\|Nael deus Darnus\\|7D5\\|","start":87,"end":92,"time":89.5,"lineNumber":31,"eventId":"21"},{"id":22,"regexType":"net","regex":"^2[12]\\|[^|]*\\|[^|]*\\|Nael deus Darnus\\|877\\|","start":92.5,"end":97.5,"time":95,"lineNumber":33,"eventId":"22"},{"id":23,"regexType":"net","regex":"^2[12]\\|[^|]*\\|[^|]*\\|Nael deus Darnus\\|7D7\\|","start":94.1,"end":99.1,"time":96.6,"lineNumber":34,"eventId":"23"},{"id":24,"regexType":"net","regex":"^2[12]\\|[^|]*\\|[^|]*\\|(?:Astral Debris|Umbral Debris)\\|7E9\\|","start":101.5,"end":106.5,"time":104,"lineNumber":35,"eventId":"24"},{"id":27,"regexType":"net","regex":"^2[12]\\|[^|]*\\|[^|]*\\|Nael deus Darnus\\|7DC\\|","start":112.9,"end":117.9,"time":115.4,"lineNumber":38,"eventId":"27"},{"id":28,"regexType":"net","regex":"^2[12]\\|[^|]*\\|[^|]*\\|Nael deus Darnus\\|7D5\\|","start":117.2,"end":122.2,"time":119.7,"lineNumber":39,"eventId":"28"},{"id":29,"regexType":"net","regex":"^2[12]\\|[^|]*\\|[^|]*\\|Nael deus Darnus\\|7D6\\|","start":127.69999999999999,"end":132.7,"time":130.2,"lineNumber":40,"eventId":"29"},{"id":30,"regexType":"net","regex":"^2[12]\\|[^|]*\\|[^|]*\\|Nael deus Darnus\\|877\\|","start":133,"end":138,"time":135.5,"lineNumber":42,"eventId":"30"},{"id":31,"regexType":"net","regex":"^2[12]\\|[^|]*\\|[^|]*\\|Nael deus Darnus\\|7D5\\|","start":137.5,"end":142.5,"time":140,"lineNumber":43,"eventId":"31"},{"id":32,"regexType":"net","regex":"^2[12]\\|[^|]*\\|[^|]*\\|Nael deus Darnus\\|7D7\\|","start":140.7,"end":145.7,"time":143.2,"lineNumber":44,"eventId":"32"},{"id":33,"regexType":"net","regex":"^2[12]\\|[^|]*\\|[^|]*\\|(?:Astral Debris|Umbral Debris)\\|7E9\\|","start":142.1,"end":147.1,"time":144.6,"lineNumber":45,"eventId":"33"},{"id":34,"regexType":"net","regex":"^2[12]\\|[^|]*\\|[^|]*\\|Nael deus Darnus\\|7DD\\|","start":143.6,"end":148.6,"time":146.1,"lineNumber":46,"eventId":"34"},{"id":35,"regexType":"net","regex":"^2[12]\\|[^|]*\\|[^|]*\\|Nael deus Darnus\\|7D8\\|","start":148.2,"end":153.2,"time":150.7,"lineNumber":47,"eventId":"35"},{"id":36,"regexType":"net","regex":"^2[12]\\|[^|]*\\|[^|]*\\|Nael deus Darnus\\|7DF\\|","start":150.1,"end":155.1,"time":152.6,"lineNumber":48,"eventId":"36"},{"id":37,"regexType":"net","regex":"^2[12]\\|[^|]*\\|[^|]*\\|Nael deus Darnus\\|7DD\\|","start":151.1,"end":156.1,"time":153.6,"lineNumber":49,"eventId":"37"},{"id":38,"regexType":"net","regex":"^2[12]\\|[^|]*\\|[^|]*\\|Nael deus Darnus\\|7D5\\|","start":160.1,"end":165.1,"time":162.6,"lineNumber":50,"eventId":"38"},{"id":39,"regexType":"net","regex":"^2[12]\\|[^|]*\\|[^|]*\\|Nael deus Darnus\\|877\\|","start":166.1,"end":171.1,"time":168.6,"lineNumber":52,"eventId":"39"},{"id":40,"regexType":"net","regex":"^2[12]\\|[^|]*\\|[^|]*\\|Nael deus Darnus\\|7D6\\|","start":174.9,"end":179.9,"time":177.4,"lineNumber":53,"eventId":"40"},{"id":41,"regexType":"net","regex":"^2[12]\\|[^|]*\\|[^|]*\\|(?:Astral Debris|Umbral Debris)\\|7E9\\|","start":175.2,"end":180.2,"time":177.7,"lineNumber":54,"eventId":"41"},{"id":42,"regexType":"net","regex":"^2[12]\\|[^|]*\\|[^|]*\\|Nael deus Darnus\\|7DA\\|","start":181.4,"end":186.4,"time":183.9,"lineNumber":55,"eventId":"42"},{"id":43,"regexType":"net","regex":"^2[12]\\|[^|]*\\|[^|]*\\|Nael Geminus\\|7DE\\|","start":183.7,"end":188.7,"time":186.2,"lineNumber":56,"eventId":"43"},{"id":44,"regexType":"net","regex":"^2[12]\\|[^|]*\\|[^|]*\\|Nael deus Darnus\\|7DC\\|","start":186.8,"end":191.8,"time":189.3,"lineNumber":57,"eventId":"44"},{"id":45,"regexType":"net","regex":"^2[12]\\|[^|]*\\|[^|]*\\|Nael deus Darnus\\|7D7\\|","start":187.9,"end":192.9,"time":190.4,"lineNumber":58,"eventId":"45"},{"id":46,"regexType":"net","regex":"^2[12]\\|[^|]*\\|[^|]*\\|Nael deus Darnus\\|7D5\\|","start":190.4,"end":195.4,"time":192.9,"lineNumber":59,"eventId":"46"},{"id":47,"regexType":"net","regex":"^2[12]\\|[^|]*\\|[^|]*\\|Nael deus Darnus\\|877\\|","start":201.4,"end":206.4,"time":203.9,"lineNumber":61,"eventId":"47"},{"id":48,"regexType":"net","regex":"^2[12]\\|[^|]*\\|[^|]*\\|Nael deus Darnus\\|7D5\\|","start":205.5,"end":210.5,"time":208,"lineNumber":62,"eventId":"48"},{"id":49,"regexType":"net","regex":"^2[12]\\|[^|]*\\|[^|]*\\|(?:Astral Debris|Umbral Debris)\\|7E9\\|","start":210.5,"end":215.5,"time":213,"lineNumber":63,"eventId":"49"},{"id":52,"regexType":"net","regex":"^2[12]\\|[^|]*\\|[^|]*\\|Nael deus Darnus\\|7DC\\|","start":223.3,"end":228.3,"time":225.8,"lineNumber":66,"eventId":"52"},{"id":53,"regexType":"net","regex":"^2[12]\\|[^|]*\\|[^|]*\\|Nael deus Darnus\\|7D6\\|","start":231.7,"end":236.7,"time":234.2,"lineNumber":67,"eventId":"53"},{"id":54,"regexType":"net","regex":"^2[12]\\|[^|]*\\|[^|]*\\|Nael deus Darnus\\|7D5\\|","start":237.1,"end":242.1,"time":239.6,"lineNumber":68,"eventId":"54"},{"id":55,"regexType":"net","regex":"^2[12]\\|[^|]*\\|[^|]*\\|Nael deus Darnus\\|877\\|","start":243.3,"end":248.3,"time":245.8,"lineNumber":70,"eventId":"55"},{"id":56,"regexType":"net","regex":"^2[12]\\|[^|]*\\|[^|]*\\|(?:Astral Debris|Umbral Debris)\\|7E9\\|","start":252.3,"end":257.3,"time":254.8,"lineNumber":71,"eventId":"56"},{"id":57,"regexType":"net","regex":"^2[12]\\|[^|]*\\|[^|]*\\|Nael deus Darnus\\|7DD\\|","start":253,"end":258,"time":255.5,"lineNumber":72,"eventId":"57"},{"id":58,"regexType":"net","regex":"^2[12]\\|[^|]*\\|[^|]*\\|Nael deus Darnus\\|7D8\\|","start":257.6,"end":262.6,"time":260.1,"lineNumber":73,"eventId":"58"},{"id":59,"regexType":"net","regex":"^2[12]\\|[^|]*\\|[^|]*\\|Nael deus Darnus\\|7DF\\|","start":259.6,"end":264.6,"time":262.1,"lineNumber":74,"eventId":"59"},{"id":60,"regexType":"net","regex":"^2[12]\\|[^|]*\\|[^|]*\\|Nael deus Darnus\\|7DD\\|","start":260.6,"end":265.6,"time":263.1,"lineNumber":75,"eventId":"60"},{"id":61,"regexType":"net","regex":"^2[12]\\|[^|]*\\|[^|]*\\|Nael deus Darnus\\|7D5\\|","start":263.9,"end":268.9,"time":266.4,"lineNumber":76,"eventId":"61"},{"id":62,"regexType":"net","regex":"^2[12]\\|[^|]*\\|[^|]*\\|Nael deus Darnus\\|7D6\\|","start":274.8,"end":279.8,"time":277.3,"lineNumber":77,"eventId":"62"},{"id":63,"regexType":"net","regex":"^2[12]\\|[^|]*\\|[^|]*\\|Nael deus Darnus\\|877\\|","start":280.5,"end":285.5,"time":283,"lineNumber":79,"eventId":"63"},{"id":64,"regexType":"net","regex":"^2[12]\\|[^|]*\\|[^|]*\\|Nael deus Darnus\\|7D5\\|","start":284.3,"end":289.3,"time":286.8,"lineNumber":80,"eventId":"64"},{"id":65,"regexType":"net","regex":"^2[12]\\|[^|]*\\|[^|]*\\|(?:Astral Debris|Umbral Debris)\\|7E9\\|","start":289.5,"end":294.5,"time":292,"lineNumber":81,"eventId":"65"},{"id":66,"regexType":"net","regex":"^2[12]\\|[^|]*\\|[^|]*\\|Nael deus Darnus\\|7DA\\|","start":291.8,"end":296.8,"time":294.3,"lineNumber":82,"eventId":"66"},{"id":67,"regexType":"net","regex":"^2[12]\\|[^|]*\\|[^|]*\\|Nael Geminus\\|7DE\\|","start":294.2,"end":299.2,"time":296.7,"lineNumber":83,"eventId":"67"},{"id":68,"regexType":"net","regex":"^2[12]\\|[^|]*\\|[^|]*\\|Nael deus Darnus\\|7DC\\|","start":297.4,"end":302.4,"time":299.9,"lineNumber":84,"eventId":"68"},{"id":69,"regexType":"net","regex":"^2[12]\\|[^|]*\\|[^|]*\\|Nael deus Darnus\\|7D5\\|","start":305.4,"end":310.4,"time":307.9,"lineNumber":85,"eventId":"69"},{"id":70,"regexType":"net","regex":"^2[12]\\|[^|]*\\|[^|]*\\|Nael deus Darnus\\|877\\|","start":311.8,"end":316.8,"time":314.3,"lineNumber":87,"eventId":"70"},{"id":71,"regexType":"net","regex":"^2[12]\\|[^|]*\\|[^|]*\\|Nael deus Darnus\\|7D6\\|","start":320.3,"end":325.3,"time":322.8,"lineNumber":88,"eventId":"71"},{"id":72,"regexType":"net","regex":"^2[12]\\|[^|]*\\|[^|]*\\|(?:Astral Debris|Umbral Debris)\\|7E9\\|","start":320.8,"end":325.8,"time":323.3,"lineNumber":89,"eventId":"72"},{"id":73,"regexType":"net","regex":"^2[12]\\|[^|]*\\|[^|]*\\|Nael Geminus\\|7DE\\|","start":329.5,"end":334.5,"time":332,"lineNumber":90,"eventId":"73"},{"id":74,"regexType":"net","regex":"^2[12]\\|[^|]*\\|[^|]*\\|Nael deus Darnus\\|7D7\\|","start":333.4,"end":338.4,"time":335.9,"lineNumber":91,"eventId":"74"},{"id":75,"regexType":"net","regex":"^2[12]\\|[^|]*\\|[^|]*\\|Nael Geminus\\|7DE\\|","start":334.5,"end":339.5,"time":337,"lineNumber":92,"eventId":"75"},{"id":76,"regexType":"net","regex":"^2[12]\\|[^|]*\\|[^|]*\\|Nael deus Darnus\\|7DC\\|","start":337.7,"end":342.7,"time":340.2,"lineNumber":93,"eventId":"76"},{"id":77,"regexType":"net","regex":"^2[12]\\|[^|]*\\|[^|]*\\|Nael deus Darnus\\|7D5\\|","start":340.7,"end":345.7,"time":343.2,"lineNumber":94,"eventId":"77"},{"id":78,"regexType":"net","regex":"^2[12]\\|[^|]*\\|[^|]*\\|Nael deus Darnus\\|877\\|","start":352.5,"end":357.5,"time":355,"lineNumber":96,"eventId":"78"},{"id":79,"regexType":"net","regex":"^2[12]\\|[^|]*\\|[^|]*\\|Nael deus Darnus\\|7D5\\|","start":356,"end":361,"time":358.5,"lineNumber":97,"eventId":"79"},{"id":80,"regexType":"net","regex":"^2[12]\\|[^|]*\\|[^|]*\\|(?:Astral Debris|Umbral Debris)\\|7E9\\|","start":361.5,"end":366.5,"time":364,"lineNumber":98,"eventId":"80"},{"id":81,"regexType":"net","regex":"^2[12]\\|[^|]*\\|[^|]*\\|Nael deus Darnus\\|7DD\\|","start":363.5,"end":368.5,"time":366,"lineNumber":99,"eventId":"81"},{"id":82,"regexType":"net","regex":"^2[12]\\|[^|]*\\|[^|]*\\|Nael deus Darnus\\|7D8\\|","start":368,"end":373,"time":370.5,"lineNumber":100,"eventId":"82"},{"id":83,"regexType":"net","regex":"^2[12]\\|[^|]*\\|[^|]*\\|Nael deus Darnus\\|7DF\\|","start":370.2,"end":375.2,"time":372.7,"lineNumber":101,"eventId":"83"},{"id":84,"regexType":"net","regex":"^2[12]\\|[^|]*\\|[^|]*\\|Nael deus Darnus\\|7DD\\|","start":371.2,"end":376.2,"time":373.7,"lineNumber":102,"eventId":"84"},{"id":86,"regexType":"net","regex":"^27\\|[^|]*\\|[^|]*\\|[^|]*\\|(?:[^|]*\\|){2}0007\\|","start":-1.6999999999999886,"end":503.3,"time":503.3,"lineNumber":109,"eventId":"86"},{"id":87,"regexType":"net","regex":"^2[12]\\|[^|]*\\|[^|]*\\|Dalamud Fragment\\|7EB\\|","start":511.79999999999995,"end":516.8,"time":514.3,"lineNumber":110,"eventId":"87"},{"id":88,"regexType":"net","regex":"^27\\|[^|]*\\|[^|]*\\|[^|]*\\|(?:[^|]*\\|){2}000[9A]\\|","start":499.29999999999995,"end":582.3,"time":582.3,"lineNumber":111,"eventId":"88"},{"id":95,"regexType":"net","regex":"^2[12]\\|[^|]*\\|[^|]*\\|Dalamud Fragment\\|7EB\\|","start":606.8,"end":611.8,"time":609.3,"lineNumber":118,"eventId":"95"},{"id":94,"regexType":"net","regex":"^27\\|[^|]*\\|[^|]*\\|[^|]*\\|(?:[^|]*\\|){2}0007\\|","start":518.3,"end":678.3,"time":598.3,"lineNumber":117,"eventId":"94"},{"id":99,"regexType":"net","regex":"^2[12]\\|[^|]*\\|[^|]*\\|Nael deus Darnus\\|83B\\|","start":696.7,"end":701.7,"time":699.2,"lineNumber":128,"eventId":"99"},{"id":100,"regexType":"net","regex":"^2[12]\\|[^|]*\\|[^|]*\\|Ragnarok\\|7E4\\|","start":-0.10000000000002274,"end":711.9,"time":701.9,"lineNumber":129,"eventId":"100"},{"id":103,"regexType":"net","regex":"^2[12]\\|[^|]*\\|[^|]*\\|Nael deus Darnus\\|7E2\\|","start":719.3,"end":724.3,"time":721.8,"lineNumber":132,"eventId":"103"},{"id":105,"regexType":"net","regex":"^2[12]\\|[^|]*\\|[^|]*\\|Nael deus Darnus\\|7E2\\|","start":741.9,"end":746.9,"time":744.4,"lineNumber":134,"eventId":"105"},{"id":106,"regexType":"net","regex":"^2[12]\\|[^|]*\\|[^|]*\\|Nael deus Darnus\\|83B\\|","start":747,"end":752,"time":749.5,"lineNumber":136,"eventId":"106"},{"id":110,"regexType":"net","regex":"^2[12]\\|[^|]*\\|[^|]*\\|Nael deus Darnus\\|7E2\\|","start":773.4,"end":778.4,"time":775.9,"lineNumber":140,"eventId":"110"},{"id":107,"regexType":"net","regex":"^2[12]\\|[^|]*\\|[^|]*\\|Ragnarok\\|7E4\\|","start":712.2,"end":792.2,"time":752.2,"lineNumber":137,"eventId":"107"},{"id":113,"regexType":"net","regex":"^2[12]\\|[^|]*\\|[^|]*\\|Nael deus Darnus\\|7E2\\|","start":796,"end":801,"time":798.5,"lineNumber":143,"eventId":"113"},{"id":114,"regexType":"net","regex":"^2[12]\\|[^|]*\\|[^|]*\\|Nael deus Darnus\\|83B\\|","start":801,"end":806,"time":803.5,"lineNumber":145,"eventId":"114"},{"id":118,"regexType":"net","regex":"^2[12]\\|[^|]*\\|[^|]*\\|Nael deus Darnus\\|7E2\\|","start":827.4,"end":832.4,"time":829.9,"lineNumber":149,"eventId":"118"},{"id":115,"regexType":"net","regex":"^2[12]\\|[^|]*\\|[^|]*\\|Ragnarok\\|7E4\\|","start":766.2,"end":846.2,"time":806.2,"lineNumber":146,"eventId":"115"},{"id":121,"regexType":"net","regex":"^2[12]\\|[^|]*\\|[^|]*\\|Nael deus Darnus\\|7E2\\|","start":850,"end":855,"time":852.5,"lineNumber":152,"eventId":"121"},{"id":122,"regexType":"net","regex":"^2[12]\\|[^|]*\\|[^|]*\\|Nael deus Darnus\\|83B\\|","start":855,"end":860,"time":857.5,"lineNumber":154,"eventId":"122"},{"id":126,"regexType":"net","regex":"^2[12]\\|[^|]*\\|[^|]*\\|Nael deus Darnus\\|7E2\\|","start":881.4,"end":886.4,"time":883.9,"lineNumber":158,"eventId":"126"},{"id":123,"regexType":"net","regex":"^2[12]\\|[^|]*\\|[^|]*\\|Ragnarok\\|7E4\\|","start":820.2,"end":900.2,"time":860.2,"lineNumber":155,"eventId":"123"},{"id":128,"regexType":"net","regex":"^2[12]\\|[^|]*\\|[^|]*\\|Nael deus Darnus\\|7E2\\|","start":904,"end":909,"time":906.5,"lineNumber":160,"eventId":"128"},{"id":129,"regexType":"net","regex":"^2[12]\\|[^|]*\\|[^|]*\\|Nael deus Darnus\\|83B\\|","start":871.5,"end":951.5,"time":911.5,"lineNumber":162,"eventId":"129","jump":857.5,"jumpType":"normal"},{"id":97,"regexType":"net","regex":"^2[12]\\|[^|]*\\|[^|]*\\|Nael deus Darnus\\|7DC\\|","start":393.6,"end":993.6,"time":693.6,"lineNumber":125,"eventId":"97"},{"id":138,"regexType":"net","regex":"^2[12]\\|[^|]*\\|[^|]*\\|Thunderwing\\|7FD\\|","start":1011.4,"end":1016.4,"time":1013.9,"lineNumber":174,"eventId":"138"},{"id":139,"regexType":"net","regex":"^2[12]\\|[^|]*\\|[^|]*\\|Nael deus Darnus\\|7DD\\|","start":1011.9,"end":1016.9,"time":1014.4,"lineNumber":175,"eventId":"139"},{"id":140,"regexType":"net","regex":"^2[12]\\|[^|]*\\|[^|]*\\|Firehorn\\|7FB\\|","start":1012.4,"end":1017.4,"time":1014.9,"lineNumber":176,"eventId":"140"},{"id":141,"regexType":"net","regex":"^2[12]\\|[^|]*\\|[^|]*\\|Nael deus Darnus\\|7DA\\|","start":1016.5,"end":1021.5,"time":1019,"lineNumber":177,"eventId":"141"},{"id":142,"regexType":"net","regex":"^2[12]\\|[^|]*\\|[^|]*\\|Thunderwing\\|7FD\\|","start":1023.4000000000001,"end":1028.4,"time":1025.9,"lineNumber":178,"eventId":"142"},{"id":143,"regexType":"net","regex":"^2[12]\\|[^|]*\\|[^|]*\\|Firehorn\\|7FB\\|","start":1024.4,"end":1029.4,"time":1026.9,"lineNumber":179,"eventId":"143"},{"id":144,"regexType":"net","regex":"^2[12]\\|[^|]*\\|[^|]*\\|Thunderwing\\|7FD\\|","start":1035.5,"end":1040.5,"time":1038,"lineNumber":180,"eventId":"144"},{"id":145,"regexType":"net","regex":"^2[12]\\|[^|]*\\|[^|]*\\|Firehorn\\|7FB\\|","start":1036.5,"end":1041.5,"time":1039,"lineNumber":181,"eventId":"145"},{"id":146,"regexType":"net","regex":"^2[12]\\|[^|]*\\|[^|]*\\|Nael deus Darnus\\|7D8\\|","start":1037.7,"end":1042.7,"time":1040.2,"lineNumber":182,"eventId":"146"},{"id":148,"regexType":"net","regex":"^2[12]\\|[^|]*\\|[^|]*\\|Nael deus Darnus\\|7DF\\|","start":1044.9,"end":1049.9,"time":1047.4,"lineNumber":184,"eventId":"148"},{"id":149,"regexType":"net","regex":"^2[12]\\|[^|]*\\|[^|]*\\|Thunderwing\\|7FD\\|","start":1047.5,"end":1052.5,"time":1050,"lineNumber":185,"eventId":"149"},{"id":150,"regexType":"net","regex":"^2[12]\\|[^|]*\\|[^|]*\\|Firehorn\\|7FB\\|","start":1048.7,"end":1053.7,"time":1051.2,"lineNumber":186,"eventId":"150"},{"id":154,"regexType":"net","regex":"^2[12]\\|[^|]*\\|[^|]*\\|Thunderwing\\|801\\|","start":1068,"end":1073,"time":1070.5,"lineNumber":190,"eventId":"154"},{"id":155,"regexType":"net","regex":"^2[12]\\|[^|]*\\|[^|]*\\|Nael Geminus\\|7DE\\|","start":1068.1,"end":1073.1,"time":1070.6,"lineNumber":191,"eventId":"155"},{"id":156,"regexType":"net","regex":"^2[12]\\|[^|]*\\|[^|]*\\|Firehorn\\|7FF\\|","start":1074.1,"end":1079.1,"time":1076.6,"lineNumber":192,"eventId":"156"},{"id":157,"regexType":"net","regex":"^2[12]\\|[^|]*\\|[^|]*\\|Nael Geminus\\|7DE\\|","start":1074.2,"end":1079.2,"time":1076.7,"lineNumber":193,"eventId":"157"},{"id":136,"regexType":"net","regex":"^2[12]\\|[^|]*\\|[^|]*\\|Nael deus Darnus\\|7E6\\|","start":0,"end":1080,"time":1000,"lineNumber":172,"eventId":"136"},{"id":158,"regexType":"net","regex":"^2[12]\\|[^|]*\\|[^|]*\\|Nael deus Darnus\\|7DC\\|","start":1078.3,"end":1083.3,"time":1080.8,"lineNumber":194,"eventId":"158"},{"id":161,"regexType":"net","regex":"^2[12]\\|[^|]*\\|[^|]*\\|Nael deus Darnus\\|7DD\\|","start":1107.9,"end":1112.9,"time":1110.4,"lineNumber":198,"eventId":"161"},{"id":162,"regexType":"net","regex":"^2[12]\\|[^|]*\\|[^|]*\\|Thunderwing\\|7FD\\|","start":1107.9,"end":1112.9,"time":1110.4,"lineNumber":199,"eventId":"162"},{"id":163,"regexType":"net","regex":"^2[12]\\|[^|]*\\|[^|]*\\|Firehorn\\|7FB\\|","start":1108.8,"end":1113.8,"time":1111.3,"lineNumber":200,"eventId":"163"},{"id":164,"regexType":"net","regex":"^2[12]\\|[^|]*\\|[^|]*\\|Nael deus Darnus\\|7DA\\|","start":1112.4,"end":1117.4,"time":1114.9,"lineNumber":201,"eventId":"164"},{"id":165,"regexType":"net","regex":"^2[12]\\|[^|]*\\|[^|]*\\|Thunderwing\\|7FD\\|","start":1120,"end":1125,"time":1122.5,"lineNumber":202,"eventId":"165"},{"id":166,"regexType":"net","regex":"^2[12]\\|[^|]*\\|[^|]*\\|Firehorn\\|7FB\\|","start":1120.9,"end":1125.9,"time":1123.4,"lineNumber":203,"eventId":"166"},{"id":167,"regexType":"net","regex":"^2[12]\\|[^|]*\\|[^|]*\\|Thunderwing\\|7FD\\|","start":1131.9,"end":1136.9,"time":1134.4,"lineNumber":204,"eventId":"167"},{"id":168,"regexType":"net","regex":"^2[12]\\|[^|]*\\|[^|]*\\|Firehorn\\|7FB\\|","start":1133,"end":1138,"time":1135.5,"lineNumber":205,"eventId":"168"},{"id":169,"regexType":"net","regex":"^2[12]\\|[^|]*\\|[^|]*\\|Nael deus Darnus\\|7D8\\|","start":1133.5,"end":1138.5,"time":1136,"lineNumber":206,"eventId":"169"},{"id":171,"regexType":"net","regex":"^2[12]\\|[^|]*\\|[^|]*\\|Nael deus Darnus\\|7DF\\|","start":1141.3,"end":1146.3,"time":1143.8,"lineNumber":208,"eventId":"171"},{"id":172,"regexType":"net","regex":"^2[12]\\|[^|]*\\|[^|]*\\|Thunderwing\\|7FD\\|","start":1144.1,"end":1149.1,"time":1146.6,"lineNumber":209,"eventId":"172"},{"id":173,"regexType":"net","regex":"^2[12]\\|[^|]*\\|[^|]*\\|Firehorn\\|7FB\\|","start":1145.2,"end":1150.2,"time":1147.7,"lineNumber":210,"eventId":"173"},{"id":177,"regexType":"net","regex":"^2[12]\\|[^|]*\\|[^|]*\\|Nael deus Darnus\\|7D8\\|","start":1161.8,"end":1166.8,"time":1164.3,"lineNumber":214,"eventId":"177"},{"id":178,"regexType":"net","regex":"^2[12]\\|[^|]*\\|[^|]*\\|Firehorn\\|7FF\\|","start":1164.6,"end":1169.6,"time":1167.1,"lineNumber":215,"eventId":"178"},{"id":179,"regexType":"net","regex":"^2[12]\\|[^|]*\\|[^|]*\\|Nael deus Darnus\\|7DD\\|","start":1165.6,"end":1170.6,"time":1168.1,"lineNumber":216,"eventId":"179"},{"id":180,"regexType":"net","regex":"^2[12]\\|[^|]*\\|[^|]*\\|Nael deus Darnus\\|7DA\\|","start":1170.2,"end":1175.2,"time":1172.7,"lineNumber":217,"eventId":"180"},{"id":181,"regexType":"net","regex":"^2[12]\\|[^|]*\\|[^|]*\\|Iceclaw\\|800\\|","start":1170.7,"end":1175.7,"time":1173.2,"lineNumber":218,"eventId":"181"},{"id":159,"regexType":"net","regex":"^2[12]\\|[^|]*\\|[^|]*\\|Nael deus Darnus\\|7E6\\|","start":1016.5999999999999,"end":1176.6,"time":1096.6,"lineNumber":196,"eventId":"159"},{"id":184,"regexType":"net","regex":"^2[12]\\|[^|]*\\|[^|]*\\|Nael deus Darnus\\|7DD\\|","start":1204.4,"end":1209.4,"time":1206.9,"lineNumber":222,"eventId":"184"},{"id":185,"regexType":"net","regex":"^2[12]\\|[^|]*\\|[^|]*\\|Thunderwing\\|7FD\\|","start":1204.5,"end":1209.5,"time":1207,"lineNumber":223,"eventId":"185"},{"id":186,"regexType":"net","regex":"^2[12]\\|[^|]*\\|[^|]*\\|Firehorn\\|7FB\\|","start":1205.4,"end":1210.4,"time":1207.9,"lineNumber":224,"eventId":"186"},{"id":187,"regexType":"net","regex":"^2[12]\\|[^|]*\\|[^|]*\\|Nael deus Darnus\\|7DA\\|","start":1208.9,"end":1213.9,"time":1211.4,"lineNumber":225,"eventId":"187"},{"id":188,"regexType":"net","regex":"^2[12]\\|[^|]*\\|[^|]*\\|Thunderwing\\|7FD\\|","start":1216.5,"end":1221.5,"time":1219,"lineNumber":226,"eventId":"188"},{"id":189,"regexType":"net","regex":"^2[12]\\|[^|]*\\|[^|]*\\|Firehorn\\|7FB\\|","start":1217.4,"end":1222.4,"time":1219.9,"lineNumber":227,"eventId":"189"},{"id":190,"regexType":"net","regex":"^2[12]\\|[^|]*\\|[^|]*\\|Thunderwing\\|7FD\\|","start":1228.5,"end":1233.5,"time":1231,"lineNumber":228,"eventId":"190"},{"id":191,"regexType":"net","regex":"^2[12]\\|[^|]*\\|[^|]*\\|Firehorn\\|7FB\\|","start":1229.6,"end":1234.6,"time":1232.1,"lineNumber":229,"eventId":"191"},{"id":192,"regexType":"net","regex":"^2[12]\\|[^|]*\\|[^|]*\\|Nael deus Darnus\\|7D8\\|","start":1230.1,"end":1235.1,"time":1232.6,"lineNumber":230,"eventId":"192"},{"id":194,"regexType":"net","regex":"^2[12]\\|[^|]*\\|[^|]*\\|Nael deus Darnus\\|7DF\\|","start":1238,"end":1243,"time":1240.5,"lineNumber":232,"eventId":"194"},{"id":195,"regexType":"net","regex":"^2[12]\\|[^|]*\\|[^|]*\\|Thunderwing\\|7FD\\|","start":1240.6,"end":1245.6,"time":1243.1,"lineNumber":233,"eventId":"195"},{"id":196,"regexType":"net","regex":"^2[12]\\|[^|]*\\|[^|]*\\|Firehorn\\|7FB\\|","start":1241.9,"end":1246.9,"time":1244.4,"lineNumber":234,"eventId":"196"},{"id":200,"regexType":"net","regex":"^2[12]\\|[^|]*\\|[^|]*\\|Thunderwing\\|801\\|","start":1261.2,"end":1266.2,"time":1263.7,"lineNumber":238,"eventId":"200"},{"id":201,"regexType":"net","regex":"^2[12]\\|[^|]*\\|[^|]*\\|Nael Geminus\\|7DE\\|","start":1261.3,"end":1266.3,"time":1263.8,"lineNumber":239,"eventId":"201"},{"id":202,"regexType":"net","regex":"^2[12]\\|[^|]*\\|[^|]*\\|Firehorn\\|7FF\\|","start":1267.1,"end":1272.1,"time":1269.6,"lineNumber":240,"eventId":"202"},{"id":203,"regexType":"net","regex":"^2[12]\\|[^|]*\\|[^|]*\\|Nael Geminus\\|7DE\\|","start":1267.4,"end":1272.4,"time":1269.9,"lineNumber":241,"eventId":"203"},{"id":182,"regexType":"net","regex":"^2[12]\\|[^|]*\\|[^|]*\\|Nael deus Darnus\\|7E6\\|","start":1113.1,"end":1273.1,"time":1193.1,"lineNumber":220,"eventId":"182"},{"id":204,"regexType":"net","regex":"^2[12]\\|[^|]*\\|[^|]*\\|Nael deus Darnus\\|7DC\\|","start":1272,"end":1277,"time":1274.5,"lineNumber":242,"eventId":"204"},{"id":96,"regexType":"net","regex":"^2[12]\\|[^|]*\\|[^|]*\\|Nael deus Darnus\\|7E7\\|","start":-16.5,"end":1383.5,"time":683.5,"lineNumber":119,"eventId":"96"},{"id":205,"regexType":"net","regex":"^2[12]\\|[^|]*\\|[^|]*\\|Nael deus Darnus\\|7E6\\|","start":1209.7,"end":2089.7,"time":1289.7,"lineNumber":244,"eventId":"205","jump":1096.6,"jumpType":"normal"},{"id":228,"regexType":"net","regex":"^2[12]\\|[^|]*\\|[^|]*\\|Nael deus Darnus\\|7E8\\|","start":0,"end":4000,"time":2000,"lineNumber":270,"eventId":"228"}],"forceJump":[],"texts":[],"ignores":{"--Reset--":true,"--sync--":true}}